Workbook

Sheet Kriteriji
A1: Ručna provjera preciznosti upita D AND E (OpenAlex) — kriteriji kodiranja
A3: Svaki zapis dobiva jednu od tri oznake:
A4: A — RELEVANTAN: bespilotna letjelica (UAV/UAS/dron) je senzorska platforma ILI predmet rada, A primjena je ekološka / okolišna: divlje životinje, staništa, šume i vegetacija u prirodnom okolišu, vode, zrak i emisije plinova, požari, obala i geomorfologija okoliša, onečišćenje, zaštićena područja, bioraznolikost.
A5: B — GRANIČAN: UAV jest platforma, ali primjena je susjedna: precizna poljoprivreda (usjevi, prinos, korovi, fenotipizacija), urbanistička/geodetska izmjera, hazardi bez ekološkog fokusa, generička UAV tehnologija koja okoliš samo spominje.
A6: C — NERELEVANTAN: nema zračne bespilotne letjelice („drone“ = trut, „UAS“ = drugi akronim, podvodni dronovi, književnost) ILI UAV bez ikakve okolišne primjene (vojna, dostava, sigurnost, softver).
A8: Postupak: (1) pročitajte naslov i sažetak; (2) ako sažetak nedostaje, otvorite poveznicu (OpenAlex ID) i pročitajte rad; (3) u stupac „KONAČNA OCJENA“ upišite A, B ili C — stupac je unaprijed popunjen prijedlogom (AI), koji je samo pomoć i može se promijeniti; (4) po potrebi napišite napomenu. List „Sažetak“ se sam preračunava.
A10: Uzorci: (a) 100 slučajnih zapisa iz cijelog razdoblja 2005.–2025. (OpenAlex sample=100, seed=20260826); (b) 50 slučajnih zapisa iz ranog razdoblja 2005.–2015. (seed=20260827) za provjeru stabilnosti preciznosti kroz vrijeme. Dohvat 27. 8. 2026.
A12: Za rad se izvještava: preciznost u strogom smislu P(A) i u širem smislu P(A ili B), s Wilsonovim 95 % intervalom; test razlike ranog i cijelog uzorka; te osjetljivost trenda na strogi upit (D AND E NOT poljoprivredni pojmovi), list „Strogi_upit“.
A14: Preporuka za drugu osobu (inter-rater): neka koautor neovisno kodira barem 30 zapisa u praznoj kopiji stupca; slaganje se izvještava kao postotak ili Cohenova kappa.

Sheet Sažetak
A1: Sažetak provjere preciznosti (sve formule; mijenja se automatski kad promijenite KONAČNU OCJENU)
A3: Uzorak A (2005.–2025., n = 100)
A4: n (ocijenjeno) | B4: =COUNTIF(Uzorak_100!$L$5:$L$104,"A")+COUNTIF(Uzorak_100!$L$5:$L$104,"B")+COUNTIF(Uzorak_100!$L$5:$L$104,"C") -> 100
A5: A — relevantan | B5: =COUNTIF(Uzorak_100!$L$5:$L$104,"A") -> 42
A6: B — graničan | B6: =COUNTIF(Uzorak_100!$L$5:$L$104,"B") -> 38
A7: C — nerelevantan | B7: =COUNTIF(Uzorak_100!$L$5:$L$104,"C") -> 20
A8: P(A) stroga preciznost | B8: =IF(B4>0,B5/B4,"") -> 0.42
A9: P(A ili B) šira preciznost | B9: =IF(B4>0,(B5+B6)/B4,"") -> 0.8
A10: Wilson 95 % donja, P(A) | B10: =IF(B4>0,((B8+1.96^2/(2*B4))-1.96*SQRT(B8*(1-B8)/B4+1.96^2/(4*B4^2)))/(1+1.96^2/B4),"") -> 0.32798225
A11: Wilson 95 % gornja, P(A) | B11: =IF(B4>0,((B8+1.96^2/(2*B4))+1.96*SQRT(B8*(1-B8)/B4+1.96^2/(4*B4^2)))/(1+1.96^2/B4),"") -> 0.51793692
A12: Wilson 95 % donja, P(A∪B) | B12: =IF(B4>0,((B9+1.96^2/(2*B4))-1.96*SQRT(B9*(1-B9)/B4+1.96^2/(4*B4^2)))/(1+1.96^2/B4),"") -> 0.71116904
A13: Wilson 95 % gornja, P(A∪B) | B13: =IF(B4>0,((B9+1.96^2/(2*B4))+1.96*SQRT(B9*(1-B9)/B4+1.96^2/(4*B4^2)))/(1+1.96^2/B4),"") -> 0.86663408
A15: Uzorak B (2005.–2015., n = 50)
A16: n (ocijenjeno) | B16: =COUNTIF(Uzorak_50_rano!$L$5:$L$54,"A")+COUNTIF(Uzorak_50_rano!$L$5:$L$54,"B")+COUNTIF(Uzorak_50_rano!$L$5:$L$54,"C") -> 50
A17: A — relevantan | B17: =COUNTIF(Uzorak_50_rano!$L$5:$L$54,"A") -> 27
A18: B — graničan | B18: =COUNTIF(Uzorak_50_rano!$L$5:$L$54,"B") -> 8
A19: C — nerelevantan | B19: =COUNTIF(Uzorak_50_rano!$L$5:$L$54,"C") -> 15
A20: P(A) stroga preciznost | B20: =IF(B16>0,B17/B16,"") -> 0.54
A21: P(A ili B) šira preciznost | B21: =IF(B16>0,(B17+B18)/B16,"") -> 0.7
A22: Wilson 95 % donja, P(A) | B22: =IF(B16>0,((B20+1.96^2/(2*B16))-1.96*SQRT(B20*(1-B20)/B16+1.96^2/(4*B16^2)))/(1+1.96^2/B16),"") -> 0.40398634
A23: Wilson 95 % gornja, P(A) | B23: =IF(B16>0,((B20+1.96^2/(2*B16))+1.96*SQRT(B20*(1-B20)/B16+1.96^2/(4*B16^2)))/(1+1.96^2/B16),"") -> 0.67030565
A24: Wilson 95 % donja, P(A∪B) | B24: =IF(B16>0,((B21+1.96^2/(2*B16))-1.96*SQRT(B21*(1-B21)/B16+1.96^2/(4*B16^2)))/(1+1.96^2/B16),"") -> 0.56249388
A25: Wilson 95 % gornja, P(A∪B) | B25: =IF(B16>0,((B21+1.96^2/(2*B16))+1.96*SQRT(B21*(1-B21)/B16+1.96^2/(4*B16^2)))/(1+1.96^2/B16),"") -> 0.80896611
A27: Razlika P(A): uzorak B (rano) − uzorak A (cijelo razdoblje)
A28: razlika udjela | B28: =B20-B8 -> 0.12
A29: z (dvoproporcijski test, združeni p) | B29: =IF(AND(B4>0,B16>0),(B20-B8)/SQRT(((B5+B17)/(B4+B16))*(1-(B5+B17)/(B4+B16))*(1/B4+1/B16)),"") -> 1.3900961
A30: p (dvostrano) | B30: =IF(B29="","",2*(1-NORMSDIST(ABS(B29)))) -> 0.1644997
A31: Tumačenje: p > 0,05 → nema dokaza da se preciznost mijenjala kroz vrijeme; trendovi i udjeli tada nisu pristrani zbog šuma upita.
A33: Napomena: formule se odnose na stupac L (KONAČNA OCJENA) oba lista; prazne ćelije se ne broje.

Sheet Uzorak_100
A1: Uzorak A: 100 slučajnih zapisa, 2005.–2025. (seed 20260826)
A2: Žuti stupac = KONAČNA OCJENA (A/B/C), popunite ili potvrdite; prijedlog (AI) je samo pomoć.
A4: # | B4: Godina | C4: Naslov | D4: Časopis / izvor | E4: OpenAlex tema | F4: OpenAlex ID (poveznica) | G4: DOI | H4: UAV pojam | I4: Sažetak (skraćen) | J4: Prijedlog (AI) | K4: Obrazloženje prijedloga | L4: KONAČNA OCJENA | M4: Napomena ocjenjivača
A5: 1 | B5: 2023 | C5: Virtual nature makes knowledge beautiful | D5: Frontiers in Virtual Reality | E5: Virtual Reality Applications and Impacts | F5: https://openalex.org/W4324088175 | G5: https://doi.org/10.3389/frvir.2023.1100540 | H5: drone | I5: This is a perspective that presents a viewpoint on immersive informal learning applications built as digital twins of the natural world. Such applications provide multimodal, interactive, immersive, embodied, and sensory experiences unique and different from typical game art environments because they are geospatial visualizations of data and information derived from ecological field plot studies, geographical information systems, drone images, and botanically correct 3D plant models visualized in real-time interactive game engines. Since they are constructed from geometric objects, they can programmatically self-express semantic data and connect to knowledge stores on the Internet to create … | J5: C | K5: Virtualna stvarnost; dronske snimke samo kao izvor podataka | L5: C
A6: 2 | B6: 2025 | C6: Eddy-covariance fluxes of CO 2 , CH 4 and N 2 O in a drained peatland forest after clear-cutting | D6: Biogeosciences | E6: Peatlands and Wetlands Ecology | F6: https://openalex.org/W4408194576 | G6: https://doi.org/10.5194/bg-22-1277-2025 | H6: uav | I6: Abstract. Rotation forestry based on clear-cut harvesting, site preparation, planting and intermediate thinnings is currently the dominant management approach in Fennoscandia. However, understanding of the greenhouse gas (GHG) emissions following clear-cutting remains limited, particularly in drained peatland forests. In this study, we report eddy-covariance-based (EC-based) net emissions of carbon dioxide (CO2), methane (CH4) and nitrous oxide (N2O) from a fertile drained boreal peatland forest 1 year after wood harvest. Our results show that, at an annual scale, the site was a net CO2 source. The CO2 emissions dominate the total annual GHG balance (23.3 t CO2 eq. ha−1 yr−1, 22.4–24.1 t CO2… | J6: A | K6: UAV spektralno snimanje tla u studiji GHG emisija tresetišta | L6: A
A7: 3 | B7: 2025 | C7: River-to-sea plastic pollution: A pilot toolbox for the Caspian Sea | D7: Chemosphere | E7: Microplastics and Plastic Pollution | F7: https://openalex.org/W4414038221 | G7: https://doi.org/10.1016/j.chemosphere.2025.144667 | H7: uav | I7: This study presents the first integrated assessment of plastic pollution at the Kura River delta, where the river enters the hydrologically enclosed Caspian Sea. We applied a modular toolbox comprising four complementary components: high-resolution hydrodynamic modeling to predict debris convergence zones, UAV-based mapping to survey shoreline conditions, automated object-based image analysis for debris detection and classification, and standardized field monitoring by trained community participants for ground-truthing and source identification. Using this framework, we identified debris accumulation hotspots and developed a replicable approach for assessing plastic pollution in semi-enclose… | J7: A | K7: UAV kartiranje plastičnog onečišćenja obale | L7: A
A8: 4 | B8: 2018 | C8: Inventory of the quantitative characteristics of single oak trees with nonparametric methods of Support Vector Machines and Decision Tree on satellite images of WorldView-2 and UAV | D8: DOAJ (DOAJ: Directory of Open Access Journals) | E8: Remote Sensing and LiDAR Applications | F8: https://openalex.org/W2892110396 | G8: https://doi.org/10.22120/jwb.2018.84168.1022 | H8: uav | I8: To achieve effective forests management it is necessary to obtain reliable statistical data like the number of stands, diameter at breast height (DBH), and ‎crown volume. While traditional methods of the forests measurements are very labor intensive and time consuming, remote sensing can provide up-to-date and low cost ‎data. In comparing ot other sensors, the satellite WV-2 ‎generate very high resolution images that can be used in the forest management practices. In the present study, we aimed to estimate parameters related on the single trees characteristics using decision tree ‎method and Support Vector Machines classification with complex matrix evaluation and Area ‎under operating chara… | J8: A | K8: Inventura hrasta, UAV + satelit, upravljanje šumama | L8: A
A9: 5 | B9: 2025 | C9: A novel waveform-based pixel decomposition method for farmland shelterbelts width extraction using Sentinel−2 multi-spectral and UAV RGB images | D9: International Journal of Digital Earth | E9: Soil erosion and sediment transport | F9: https://openalex.org/W4417196979 | G9: https://doi.org/10.1080/17538947.2025.2584509 | H9: uav | I9: As vital components of the Three-North Shelter Forest Program, farmland shelterbelts play a critical role in enhancing agricultural resilience. Among their structural attributes, shelterbelt width stands out as a key parameter that directly influences their ecological effectiveness. This study proposed a novel waveform-based pixel decomposition method (WBPD) for extracting the shelterbelt width. By integrating Sentinel−2 images with UAV-derived orthophoto maps, we extracted fractional coverage (FC) waveforms and enhanced width estimation through refined pixel decomposition. The main findings are as follows: (1) The dimidiate pixel model accurately estimated FC (R² = 0.764, RMSE = 0.15), with… | J9: A | K9: Širina šumskih pojaseva, UAV RGB (ekološka funkcija) | L9: A
A10: 6 | B10: 2022 | C10: Correlation of UAV and satellite-derived vegetation indices with cotton physiological parameters and their use as a tool for scheduling variable rate irrigation in cotton | D10: Precision Agriculture | E10: Remote Sensing in Agriculture | F10: https://openalex.org/W4293531406 | G10: https://doi.org/10.1007/s11119-022-09948-6 | H10: uav, unmanned aerial | I10: Abstract Current irrigation management zones (IMZs) for variable rate irrigation (VRI) systems are static. They are delineated in the beginning of the season and used thereafter. However, recent research has shown that IMZ boundaries are transient and change with time during the growing season. The primary goal of this study was to explore the potential of using vegetation indices (VIs) developed from unmanned aerial vehicle (UAV) and satellite images to predict cotton physiological parameters that can be used to delineate in-season boundaries of IMZs. A 2 year study was conducted in a 38 ha commercial cotton field in southwestern Georgia, USA. Throughout the two growing seasons, VIs were ca… | J10: B | K10: Precizna poljoprivreda: pamuk, navodnjavanje | L10: B
A11: 7 | B11: 2019 | C11: Morphometric characterization of the stingless bees, Tetragonula iridipennis Smith (Hymenoptera: Apidae) | D11: Journal of Entomology and Zoology Studies | E11: Plant and animal studies | F11: https://openalex.org/W3088000011 | H11: drone, drones | I11: Although, a good diversity of Tetragonula iridipennis is occurred in Northern Parts of the country, still very less studies have been conduced to explore their habitat and morphological features. Again, morphometry of drones of T. iridipennis is first time recorded in Temperate region/ Northern Parts of India. As by appearance, drone and worker bees look quite similar in appearance, the measurements of drone will help to distinguish them from worker bees. The studies will helpful in colonizing their feral colonies into hives and to design a suitable hives for their domestication.Significant differences were found in various body parts of all three castes. Further, results showed an important… | J11: C | K11: „Drone“ = trut (pčele) | L11: C
A12: 8 | B12: 2020 | C12: Evaluating the Use of Drones Equipped with Thermal Sensors as an Effective Method for Estimating Wildlife | D12: Wildlife Society Bulletin | E12: Wildlife Ecology and Conservation | F12: https://openalex.org/W3021841073 | G12: https://doi.org/10.1002/wsb.1090 | H12: drone, drones | I12: ABSTRACT Drones equipped with thermal sensors have shown ability to overcome some of the limitations often associated with traditional human‐occupied aerial surveys (e.g., low detection, high operational cost, human safety risk). However, their accuracy and reliability as a valid population technique have not been adequately tested. We tested the effectiveness of using a miniaturized thermal sensor equipped to a drone (thermal drone) for surveying white‐tailed deer ( Odocoileus virginianus ) populations using a captive deer population with a highly constrained (hereafter, known) abundance (151–163 deer, midpoint 157 [87–94 deer/km 2 , midpoint 90 deer/km 2 ]) at Auburn University's deer rese… | J12: A | K12: Termalni dronovi za popis divljači | L12: A
A13: 9 | B13: 2025 | C13: Advancing Water Hyacinth Recognition: Integration of Deep Learning and Multispectral Imaging for Precise Identification | D13: Remote Sensing | E13: Coastal wetland ecosystem dynamics | F13: https://openalex.org/W4407704902 | G13: https://doi.org/10.3390/rs17040689 | H13: drone | I13: The aquatic plant species Eichhornia crassipes, commonly known as water hyacinth, is indigenous to South America and is considered an invasive species. The invasive water hyacinth has caused significant economic and ecological damage by preventing sunlight from penetrating the surface of the water, resulting in the loss of aquatic life. To quantify the invasiveness and address the issue of accurately identifying plant species, water hyacinths have prompted numerous researchers to propose approaches to detect regions occupied by water hyacinths. One such solution involves the utilization of multispectral imaging which obtain detailed information about plant species based on the surface reflec… | J13: A | K13: Invazivna vodena biljka, dron + duboko učenje | L13: A
A14: 10 | B14: 2024 | C14: Semantic Segmentation in Large-Size Orthomosaics to Detect the Vegetation Area in Opuntia spp. Crop | D14: Journal of Imaging | E14: Botanical Research and Applications | F14: https://openalex.org/W4401206527 | G14: https://doi.org/10.3390/jimaging10080187 | H14: drones | I14: This study focuses on semantic segmentation in crop Opuntia spp. orthomosaics; this is a significant challenge due to the inherent variability in the captured images. Manual measurement of Opuntia spp. vegetation areas can be slow and inefficient, highlighting the need for more advanced and accurate methods. For this reason, we propose to use deep learning techniques to provide a more precise and efficient measurement of the vegetation area. Our research focuses on the unique difficulties posed by segmenting high-resolution images exceeding 2000 pixels, a common problem in generating orthomosaics for agricultural monitoring. The research was carried out on a Opuntia spp. cultivation located … | J14: B | K14: Poljoprivredna kultura Opuntia, segmentacija | L14: B
A15: 11 | B15: 2021 | C15: Evaluating eco-environment in urban agglomeration from a vegetation-impervious surface-soil-air framework: an example in Ningxia, China | D15: Journal of Applied Remote Sensing | E15: Urban Heat Island Mitigation | F15: https://openalex.org/W3138645229 | G15: https://doi.org/10.1117/1.jrs.15.014518 | H15: uas | I15: Urban agglomerations (UA) are the fastest growing regional types during recent years, especially in developing countries. Monitoring and evaluating the eco-environment quality of UA is significant for sustainability. The previous remote sensing models of urban eco-environment are generally based on the vegetation-impervious surface-soil framework, which neglects the air quality in urban areas. We constructed a vegetation-impervious surface-soil-air (VISA) framework and derived a remote sensing model of UA eco-environment (RSUAE) based on the VISA. The RSUAE can integrate the greenness, dryness and imperviousness, moisture, heat, and air turbidity. The new model was evaluated by comparing wit… | J15: C | K15: „UAS“ = urban agglomerations, nema letjelice | L15: C
A16: 12 | B16: 2024 | C16: Identification and Monitoring of Crop Pests and Diseases Based on Remote Sensing Technology | D16: Transactions on Environment Energy and Earth Sciences | E16: Remote Sensing and Land Use | F16: https://openalex.org/W4405388873 | G16: https://doi.org/10.62051/btdqj764 | H16: uav | I16: Identifying and monitoring crop pests and diseases are crucial to agricultural production, and they directly affect crop growth and the quality of agricultural products. This paper reviews crop pest and disease identification and monitoring techniques based on remote sensing imagery, emphasizing their advantages in providing timely and accurate information. The paper mainly summarizes the data sources for crop pest and disease detection, including satellite, UAV, aircraft, ground, and aerial remote sensing data, as well as laboratory monitoring data and seven types of multi-source data fusion. Four remote sensing monitoring techniques were discussed: spectral reflectance analysis, vegetation… | J16: B | K16: Pregled daljinskih istraživanja štetnika usjeva; UAV kao jedan izvor | L16: B
A17: 13 | B17: 2020 | C17: Contribution of Lightweight Revolving Laser Scanner, HiRes UAV LiDARs and Photogrammetry for Characterization of Coastal Aeolian Morphologies | D17: Journal of Coastal Research | E17: Aeolian processes and effects | F17: https://openalex.org/W3015499049 | G17: https://doi.org/10.2112/si95-213.1 | H17: uav | I17: Garcin, M.; Desmazes, F.; Nicolae Lerma, A.; Gouguet, L., and Météreau, V., 2020. Contribution of Lightweight Revolving Laser Scanner, HiRes UAV LiDARs and photogrammetry for characterization of coastal aeolian morphologies. In: Malvárez, G. and Navas, F. (eds.), Global Coastal Issues of 2020. Journal of Coastal Research, Special Issue No. 95, pp. 1094–1100. Coconut Creek (Florida), ISSN 0749-0208.The monitoring of coastal dunes changes in a context of climate change is a major issue for assessment of coastal hazards. While shoreline retreat and beach erosion are generally well characterized within coastal observatories, the monitoring of dunes changes under aeolian-driven processes are freq… | J17: A | K17: Obalne dine, UAV LiDAR i fotogrametrija | L17: A
A18: 14 | B18: 2025 | C18: UAV Photogrammetry-Based Leaf Area Index for Above-Ground Biomass Estimation in Wetlands | D18: IEEE Journal of Selected Topics in Applied Earth Observations and Remote Sensing | E18: Remote Sensing and LiDAR Applications | F18: https://openalex.org/W4409261290 | G18: https://doi.org/10.1109/jstars.2025.3558893 | H18: uav | I18: Wetlands are highly productive and biologically diverse environments that provide numerous ecosystem services. Effective monitoring methods are critical to ensure their preservation and management. This paper used UAV-derived RGB images and SfM photogrammetry to create point clouds. Primary tie points were utilized as they are the more suitable representation of the raw 3D information of the common features from the overlapping images. A Leaf Area Index (LAI) estimation workflow for LiDAR was then tested on the UAV-SfM point cloud of two wetland types – alpine peatland and coastal salt marsh- to assess its applicability. The LAI and AGB values for the peatland were 0.75 – 2.58 and 0 – 318.8 … | J18: A | K18: Biomasa močvara UAV fotogrametrijom | L18: A
A19: 15 | B19: 2021 | C19: An Improved Multi-Platform Stacked D-InSAR Method for Monitoring the Three-Dimensional Deformation of the Mining Area | D19: IEEE Access | E19: Synthetic Aperture Radar (SAR) Applications and Techniques | F19: https://openalex.org/W3158257030 | G19: https://doi.org/10.1109/access.2021.3076065 | H19: unmanned aerial | I19: The acquisition of information on fine surface three-dimensional deformation in a goaf is of great significance for the in-depth understanding of the law of mining subsidence and guiding the safe production and ecological restoration of the mining area. In this paper, three platform SAR satellite images are used for stacked D-InSAR processing to obtain the information on surface deformation in three line-of-sight directions. An improved three-dimensional decomposition model is proposed based on the difference between the COSMO-SkyMed and TerraSAR-X satellite heading angles, which are very small. The proposed method is verified by evaluating the three-dimensional deformation of the ground sur… | J19: B | K19: Deformacije rudarskog područja, UAV fotogrametrija kao pomoćni podatak | L19: B
A20: 16 | B20: 2023 | C20: Investigation of Combining Deep Learning Object Recognition with Drones for Forest Fire Detection and Monitoring | D20: International Journal of Advanced Computer Science and Applications | E20: Fire Detection and Safety Systems | F20: https://openalex.org/W4362571254 | G20: https://doi.org/10.14569/ijacsa.2023.0140342 | H20: drones, uavs, unmanned aerial | I20: Forest fires are a global environmental problem that can cause significant damage to natural resources and human lives. The increasing frequency and severity of forest fires have resulted in substantial losses of natural resources. To mitigate this, an effective fire detection and monitoring system is crucial. This work aims to explore and review the current advancement in the field of forest fire detection and monitoring using both drones or unmanned aerial vehicles (UAVs), and deep learning techniques. The utilization of drones fully equipped with specific sensors and cameras provides a cost-effective and efficient solution for real-time monitoring and early fire detection. In this paper, … | J20: A | K20: Detekcija šumskih požara dronovima | L20: A
A21: 17 | B21: 2024 | C21: Population Size and Spatial Distribution of the Mexican Blind Cavefish (Astyanax) within the Caves | D21: Fishes | E21: Subterranean biodiversity and taxonomy | F21: https://openalex.org/W4401894579 | G21: https://doi.org/10.3390/fishes9090334 | H21: drones | I21: The most studied cavefish in the world is Astyanax mexicanus, and the most frequently used specimens in research come from the Pachón cave in Northeast Mexico. A recent study using the capture–mark–recapture technique revealed that the Pachón population size is only in the hundreds of individuals, not in the thousands. This result raises serious concerns about their long-term survival and highlights the need to accurately estimate the population size of other Astyanax caves. In our study, we used a well-established, non-invasive method for estimating population size: the transect sampling method, which counts the abundance of organisms along a line at regular intervals. We used the 310 m lon… | J21: A | K21: Populacija špiljske ribe, dronovi u nepristupačnim galerijama | L21: A
A22: 18 | B22: 2021 | C22: Comparison of Outdoor Compost Pile Detection Using Unmanned Aerial Vehicle Images and Various Machine Learning Techniques | D22: Drones | E22: Remote Sensing and LiDAR Applications | F22: https://openalex.org/W3157060625 | G22: https://doi.org/10.3390/drones5020031 | H22: uav, unmanned aerial | I22: Since outdoor compost piles (OCPs) contain large amounts of nitrogen and phosphorus, they act as a major pollutant that deteriorates water quality, such as eutrophication and green algae, when the OCPs enter the river during rainfall. In South Korea, OCPs are frequently used, but there is a limitation that a lot of manpower and budget are consumed to investigate the current situation, so it is necessary to efficiently investigate the OCPs. This study compared the accuracy of various machine learning techniques for the efficient detection and management of outdoor compost piles (OCPs), a non-point pollution source in agricultural areas in South Korea, using unmanned aerial vehicle (UAV) image… | J22: A | K22: Detekcija kompostnih hrpi (zaštita voda) UAV-om | L22: A
A23: 19 | B23: 2024 | C23: Review of microclimate mapping methods in forestry | D23: Revista de la Facultad de Agronomía | E23: Remote Sensing and LiDAR Applications | F23: https://openalex.org/W4405805956 | G23: https://doi.org/10.47280/revfacagron(luz).v42.n1.iv | H23: drones, uav, uas, rpas | I23: The study of microclimates provides a several benefits that imply their importance to reduce the effects of climate change, so the mapping of microclimates emerges as an alternative for their identification and conservation. The objective of this review is to identify the techniques used in microclimate mapping. The methodology used was an exploratory review in databases such as Science Direct, Springer and IEEXplore, which determined that there is a shortage of works related to microclimate mapping, since only 19 works met the inclusion requirements of the review. It was determined that the main objective of the microclimate mapping focused on the tree canopy, the height and density of the … | J23: A | K23: Pregled kartiranja mikroklime u šumarstvu, uklj. dronove | L23: A
... A31: 27 | B31: 2023 | C31: Instance segmentation method for weed detection using UAV imagery in soybean fields | D31: Computers and Electronics in Agriculture | E31: Smart Agriculture and AI | F31: https://openalex.org/W4381435793 | G31: https://doi.org/10.1016/j.compag.2023.107994 | H31: uav | I31: (sažetak nije dostupan — otvoriti poveznicu) | J31: B | K31: Korovi u soji | L31: B
A32: 28 | B32: 2024 | C32: Drones and technopreneurship in Malaysia: unlocking the economic potential of drones in built environment development | D32: Universiti Putra Malaysia Institutional Repository (Universiti Putra Malaysia) | E32: UAV Applications and Optimization | F32: https://openalex.org/W7155285149 | H32: drone, drones, unmanned aerial | I32: Drones, with diverse technological capabilities, are poised to revolutionise various traditional tasks, particularly in-built environment development while driving economic growth, innovation, and job creation. Within the Malaysian context, drones have evolved beyond recreational use to become sophisticated unmanned aerial vehicles with untapped business potential. Against this backdrop, this paper explores a comprehensive review of drone development in Malaysia. Using a multidisciplinary approach, the review includes selected publication data from academic journals and online media published between 2018 and 2023, complemented with insights gathered from expert interviews. Aiming to bridge … | J32: C | K32: Poduzetništvo s dronovima | L32: C
A33: 29 | B33: 2025 | C33: Review of Technologies and Architectures for UAV-Air Quality Monitoring in Hazardous Environments | D33: Zenodo (CERN European Organization for Nuclear Research) | E33: UAV Applications and Optimization | F33: https://openalex.org/W7117579206 | G33: https://doi.org/10.5281/zenodo.18080722 | H33: uav, uavs, unmanned aerial | I33: Certain technologies enable remote monitoring in hazardous environments. These technologies range from wired and wireless communication, sensors, IoT, waste management, and cloud technologies. This paper reviews the technologies and architectures for Unmanned Aerial Vehicles' air quality monitoring systems in hazardous environments. It exposes the technologies and protocols associated with the UAV hardware, gas sensing, storage, and transmission. This paper identifies and discusses UAVs in air quality monitoring, IoT, wired and wireless communication technologies, choices, and applications in air quality monitoring in Hazardous environments. | J33: A | K33: Pregled UAV sustava za praćenje kakvoće zraka | L33: A
A34: 30 | B34: 2025 | C34: Strategic AI-Oriented Compliance Optimization Models for FinTechs Operating Across Multi-Jurisdictional Financial Ecosystems | D34: International Journal of Advanced Multidisciplinary Research and Studies | E34: FinTech, Crowdfunding, Digital Finance | F34: https://openalex.org/W4412640527 | G34: https://doi.org/10.62225/2583049x.2025.5.4.4592 | H34: (nije u naslovu/sažetku) | I34: The expansion of FinTech enterprises across international financial ecosystems has introduced complex compliance challenges stemming from heterogeneous regulatory environments. This review investigates the strategic deployment of Artificial Intelligence (AI) to enhance regulatory compliance across jurisdictions, focusing on automation, adaptability, and real-time responsiveness. It explores AI-driven frameworks—including Natural Language Processing (NLP), Machine Learning (ML), and Robotic Process Automation (RPA)—to optimize regulatory interpretation, anti-money laundering (AML) procedures, and Know Your Customer (KYC) requirements. The study further examines how AI models facilitate risk-b… | J34: C | K34: FinTech; nema UAV pojma u naslovu/sažetku | L34: C
A35: 31 | B35: 2021 | C35: Quantifying Waterfowl Numbers: Comparison of Drone and Ground-Based Survey Methods for Surveying Waterfowl on Artificial Waterbodies | D35: Drones | E35: Wildlife Ecology and Conservation | F35: https://openalex.org/W3119555133 | G35: https://doi.org/10.3390/drones5010005 | H35: drone, drones | I35: Drones are becoming a common method for surveying wildlife as they offer an aerial perspective of the landscape. For waterbirds in particular, drones can overcome challenges associated with surveying locations not accessible on foot. With the rapid uptake of drone technology for bird surveys, there is a need to compare and calibrate new technologies with existing survey methods. We compared waterfowl counts derived from ground- and drone-based survey methods. We sought to determine if group size and waterbody size influenced the difference between counts of non-nesting waterfowl and if detection of species varied between survey methods. Surveys of waterfowl were carried out at constructed ir… | J35: A | K35: Dron vs. terenski popis vodenih ptica | L35: A
A36: 32 | B36: 2025 | C36: Evaluating temporal trends in behavior and demographics to understand the lack of recovery of an endangered whale population | D36: Mspace (University of Manitoba) | E36: Marine animal studies overview | F36: https://openalex.org/W7137536149 | H36: drone | I36: Beluga whales (Delphinapterus leucas) are critical components of the Arctic marine ecosystem, and they face numerous threats from environmental changes and human activities. Understanding their population dynamics, habitat use, and social structure is crucial for their conservation. The research outlined here investigates the endangered Cumberland Sound beluga whale population using various techniques including drone surveys, aerial surveys, and satellite telemetry. The thesis begins with an overview of beluga whale ecology, behavior, and the threats they face, and explores how many of these aspects vary between populations. Satellite telemetry was used to explore behavioral trends, revealin… | J36: A | K36: Beluge, dronski popisi | L36: A
A37: 33 | B37: 2023 | C37: TLS2trees : A scalable tree segmentation pipeline for TLS data | D37: Methods in Ecology and Evolution | E37: Remote Sensing and LiDAR Applications | F37: https://openalex.org/W4387845585 | G37: https://doi.org/10.1111/2041-210x.14233 | H37: uav | I37: Abstract Above‐ground biomass (AGB) is an important metric used to quantify the mass of carbon stored in terrestrial ecosystems. For forests, this is routinely estimated at the plot scale (typically 1 ha) using inventory measurements and allometry. In recent years, terrestrial laser scanning (TLS) has appeared as a disruptive technology that can generate a more accurate assessment of tree and plot scale AGB; however, operationalising TLS methods has had to overcome a number of challenges. One such challenge is the segmentation of individual trees from plot level point clouds that are required to estimate woody volume, this is often done manually (e.g. with interactive point cloud editing sof… | J37: B | K37: TLS segmentacija stabala; UAV spomenut kao proširenje | L37: B
A38: 34 | B38: 2024 | C38: Old-growth mapping in Patagonia’s evergreen forests must integrate GEDI data to overcome NFI data limitations and to effectively support biodiversity conservation | D38: Forest Ecology and Management | E38: Remote Sensing and LiDAR Applications | F38: https://openalex.org/W4400416837 | G38: https://doi.org/10.1016/j.foreco.2024.122059 | H38: (nije u naslovu/sažetku) | I38: (sažetak nije dostupan — otvoriti poveznicu) | J38: B | K38: Kartiranje prašuma GEDI; sažetak nedostupan (provjeriti) | L38: B
A39: 35 | B39: 2024 | C39: Enhancing security and safety in quadcopter drones through unsupervised machine learning | D39: UVic’s Research and Learning Repository (University of Victoria) | E39: UAV Applications and Optimization | F39: https://openalex.org/W7199743103 | H39: drone, drones | I39: The increasing deployment of drones in various sectors has raised significant security concerns regarding their vulnerability to cyber-attacks and sensor data manipulation. Our project presents a comprehensive anomaly detection system designed to enhance drone security and safety through unsupervised machine learning. The implementation utilized a custom drone platform based on open-source components, enabling complete access to system internals and sensor data for security monitoring. Through systematic vulnerability analysis and testing, the project collected an extensive dataset comprising approximately 11.5 million network traffic samples and 1.25 million MAVLink messages, representing b… | J39: C | K39: Sigurnost kvadkoptera | L39: C
A40: 36 | B40: 2018 | C40: Elevate: Autonomous Pollution Surveillance System | D40: Automation and Autonomous Systems | E40: Air Quality Monitoring and Forecasting | F40: https://openalex.org/W2898544168 | H40: drone | I40: Epidemiological studies have shown that a close association is found between elevated air pollution levels and exacerbating cases of cardiovascular and respiratory diseases among older people and kids. Moreover, the presence of fine particulate in air makes it un-healthy to breathe which leads to lung cancer and cardiopulmonary mortality. Thus, in order to deploy effective air pollution control strategies, it is necessary to keep track of air quality levels throughout the day. The technology enabled solutions are required to collect and analyze air quality. In this research article, a novel hardware named “Elevate” has been proposed with aim to monitor air quality over a period of time. Basi… | J40: A | K40: Dron za nadzor onečišćenja zraka | L40: A
A41: 37 | B41: 2024 | C41: Monitoring and zoning soybean maturity using UAV remote sensing | D41: Industrial Crops and Products | E41: Remote Sensing in Agriculture | F41: https://openalex.org/W4402081459 | G41: https://doi.org/10.1016/j.indcrop.2024.119470 | H41: uav | I41: (sažetak nije dostupan — otvoriti poveznicu) | J41: B | K41: Zrelost soje | L41: B
A42: 38 | B42: 2025 | C42: Progress in the application of remote sensing for water quality and human health mapping in informal settlements of South Africa: A review | D42: Scientific African | E42: Water Quality and Pollution Assessment | F42: https://openalex.org/W4409994142 | G42: https://doi.org/10.1016/j.sciaf.2025.e02718 | H42: uavs, unmanned aerial | I42: Informal settlements in South Africa are a part of the urban landscape which is impossible to ignore due to their socio-economic contribution to the urban economies. However, the rapid expansion of these settlements exposes the population to various environmental hazards such as floods, pollution, and waterborne diseases and thus requires continuous monitoring. The use of remote sensing data has proved very effective for mapping water bodies, water quality, flood risk and water-borne diseases in parts of the world and in South Africa. This review highlights the extent to which remote sensing technology was used for mapping water quality in informal settlements, water-borne diseases, challeng… | J42: A | K42: Kakvoća vode u neformalnim naseljima; UAV preporučen | L42: A
A43: 39 | B43: 2025 | C43: Automated sugar beet seedling detection and mapping using a UAV-borne RGB camera and deep learning techniques | D43: Agroinženeriâ | E43: Remote Sensing in Agriculture | F43: https://openalex.org/W7117460984 | G43: https://doi.org/10.26897/2687-1149-2025-6-4-16 | H43: uav, uavs, unmanned aerial | I43: Accurate and timely assessment of plant stand density is crucial for modern crop production, directly impacting sugar beet yield and profitability. This study aims to develop and validate a highly accurate automated method for counting sugar beet seedlings using unmanned aerial vehicles (UAVs) and deep learning algorithms, optimizing both precision and processing speed. Field experiments were conducted in 2025 on commercial sugar beet fields in the Buzdyak district of the Republic of Bashkortostan. A DJI Phantom 4 Pro UAV equipped with an RGB camera captured aerial imagery from a 20-meter altitude. Initial vegetation segmentation employed the Excess Green (ExG) index, followed by binarizatio… | J43: B | K43: Šećerna repa, brojanje sadnica | L43: B
A44: 40 | B44: 2016 | C44: Urban stream deserts: Mapping a legacy of urbanization in the United States | D44: Applied Geography | E44: Land Use and Ecosystem Services | F44: https://openalex.org/W2222420283 | G44: https://doi.org/10.1016/j.apgeog.2015.12.008 | H44: (nije u naslovu/sažetku) | I44: (sažetak nije dostupan — otvoriti poveznicu) | J44: B | K44: Urbani potoci; sažetak nedostupan (provjeriti) | L44: B
A45: 41 | B45: 2024 | C45: UAV remote sensing phenotyping of wheat collection for response to water stress and yield prediction using machine learning | D45: Plant Stress | E45: Remote Sensing in Agriculture | F45: https://openalex.org/W4394960550 | G45: https://doi.org/10.1016/j.stress.2024.100464 | H45: uav | I45: Water stress is a significant challenge for global food production. Rainfall pattern is becoming unpredictable due to climate change that causes unprecedent water stress conditions in cereals production including wheat which is one of the important staple food crops. To sustain wheat production under water limiting conditions, there is an urgent need to develop drought-tolerant wheat varieties. For this, screening large numbers of wheat genotype for traits related to growth and yield under water stressed conditions is crucial. In this study, we deployed high-throughput phenotyping approaches, including uncrewed aerial vehicle (UAV)-based multispectral imaging, advanced machine and deep learn… | J45: B | K45: Fenotipizacija pšenice | L45: B
A46: 42 | B46: 2012 | C46: Computational Study on Micro-Pilot Flame Ignition Strategy for a Direct Injection Stratified Charge Rotary Engine | D46: CORE Scholar (Wright State University) | E46: Advanced Combustion Engine Technologies | F46: https://openalex.org/W2222754784 | H46: uav, unmanned aerial | I46: The Office of Security of Defense's Assured Fuels Initiative has recently been pressing for a single fuel battle space. This endeavor requires modifying many of the vehicle power plants currently in operation throughout the Armed Forces. The RQ-7 Shadow, an unmanned aerial vehicle (UAV) utilized by the Marine Corp and Army for reconnaissance purposes, is powered by UEL's AR741 rotary engine and functions on aviation fuel. One effort underway has been focused on developing this rotary engine system to operate on heavy fuels using direct injection technology and charge stratification. Although the rotary engine has many advantages over standard reciprocating engines, providing a reliable ignit… | J46: C | K46: Motor vojnog UAV-a | L46: C
A47: 43 | B47: 2025 | C47: An Overview of Unmanned Aerial Vehicles Technologies for Office Use and Services Delivery | D47: FUDMA Journal of Engineering and Technology | E47: UAV Applications and Optimization | F47: https://openalex.org/W7166539008 | G47: https://doi.org/10.33003/sx3s2787 | H47: drone, drones, unmanned aerial | I47: Universities are transforming into smart ecosystems driven (SED) by technology, transforming office logistics from inefficient processes to faster, more efficient, and innovative ones, thereby enhancing modern communication. Quadcopter drones (QCD) with delivery systems are revolutionizing office logistics by increasing efficiency, reducing costs, and boosting productivity. The paper explores the feasibility and functionality of a drone-based system for autonomously transporting small office items, aiming to improve efficiency, reduce human effort, and provide a reliable, secure intra-office delivery method. Unmanned Aerial Vehicles (drones) are transforming office spaces by eliminating huma… | J47: C | K47: Dostava u uredima | L47: C
A48: 44 | B48: 2023 | C48: The Role of Cold-Water Thermal Refuges for Stream Salmonids in a Changing Climate—Experiences from Atlantic Canada | D48: Fishes | E48: Fish Ecology and Management Studies | F48: https://openalex.org/W4386966520 | G48: https://doi.org/10.3390/fishes8090471 | H48: drone | I48: Thermal refuges are becoming increasingly influential for dictating the population status and spatial distribution of cold-water stenotherm salmonids in the mid- to southern extent of their range. The global climate is predicted to continue to warm, and therefore, the overall thermal suitability of freshwater habitats for stream salmonids is predicted to decline in concert. However, stream and river thermal heterogeneity will offer considerable resiliency for these populations. Thermal refuges are formed by many physical processes; common natural refuges include cold tributary plumes, groundwater springs, alcoves, and hyporheic upwellings. However, many anthropogenically formed refuges (such… | J48: A | K48: Termalni refugiji salmonida; dronske termalne kamere | L48: A
A49: 45 | B49: 2025 | C49: Iterative Morphological Filtering for DEM Generation: Improving Accuracy and Robustness in Complex Terrains | D49: Applied Sciences | E49: Remote Sensing and LiDAR Applications | F49: https://openalex.org/W4415811117 | G49: https://doi.org/10.3390/app152111683 | H49: uav | I49: Accurate terrain modeling from high-resolution digital surface models (DSM) is critical for geosciences, geology, geomorphology, earthquake studies, and applied geology. However, existing filtering methods such as progressive morphological filtering (PMF), cloth simulation filtering (CSF), and progressive TIN densification (TIN) often struggle with complex topography and urban structures, leading to either excessive ground loss or incomplete object removal. Furthermore, some of these algorithms are only specialized for point cloud data and are not optimized for grid data. To address these limitations, we propose an iterative morphological filtering (IMF) algorithm that introduces a binary su… | J49: B | K49: Filtriranje DEM-a (geoznanosti) | L49: B
A50: 46 | B50: 2025 | C50: Advancing crocodiles conservation through aerial ecological monitoring with drones in West Africa | D50: Journal of Entomology and Zoology Studies | E50: Fish Biology and Ecology Studies | F50: https://openalex.org/W4414883922 | G50: https://doi.org/10.22271/j.ento.2025.v13.i5a.9609 | H50: drone, drones | I50: Crocodilians play an essential ecological role in West African freshwater ecosystems. However, monitoring them remains difficult due to their secretive behaviour and inaccessible habitats. This study examines the potential of using drones to monitor populations of the species Crocodylus suchus in a sacred pool in northern Benin. During the study, drone flights were conducted at various altitudes (15, 30 and 50 meters), speeds (0 and 2 meters per second) and approach angles (vertical and oblique). Environmental conditions such as land cover, contrast between the animals and the landscape, and observer effort were also assessed. A total of 54 flights were conducted to collect image and video s… | J50: A | K50: Krokodili, dronski monitoring | L50: A
A51: 47 | B51: 2023 | C51: Digital Phenotyping in Plant Breeding: Evaluating Relative Maturity, Stand Count, and Plant Height in Dry Beans via RGB Drone-Based Imagery and Deep Learning Approaches | D51: Zenodo (CERN European Organization for Nuclear Research) | E51: Smart Agriculture and AI | F51: https://openalex.org/W4383863871 | G51: https://doi.org/10.5281/zenodo.7922589 | H51: drone, uas | I51: The datasets included were collected from the MSU dry bean breeding project sites in planting seasons 2020, 2021 and 2022. Specific planting season includes the digital surface models (DSM), digital terrain model (DTM) or point cloud (PC) from above and soil level generated using the raw images, plot boundary delimitations (.shp), and the ground-truth notes to plant height (PH) estimation. /2020: This directory contains 4 folders /a._Ground_notes 1. 2020 N&B Raw.xlsx Ground truth notes collected in 2020 at SVREC location for Black and Navy bean market classes. /b._Shapefiles Plot boundaries files (.shp) and field area from 2020 SVREC location containing plot level information using the breed… | J51: B | K51: Fenotipizacija graha (skup podataka) | L51: B
A52: 48 | B52: 2021 | C52: Preliminary analysis of landslide hazard in Brunei Darussalam, SE Asia | D52: Environmental Earth Sciences | E52: Landslides and related hazards | F52: https://openalex.org/W3188337667 | G52: https://doi.org/10.1007/s12665-021-09815-z | H52: (nije u naslovu/sažetku) | I52: (sažetak nije dostupan — otvoriti poveznicu) | J52: B | K52: Klizišta Brunei; sažetak nedostupan (provjeriti) | L52: B
A53: 49 | B53: 2025 | C53: Real-Time Vision–Language Analysis for Autonomous Underwater Drones: A Cloud–Edge Framework Using Qwen2.5-VL | D53: Drones | E53: Underwater Vehicles and Communication Systems | F53: https://openalex.org/W4413773129 | G53: https://doi.org/10.3390/drones9090605 | H53: drone, drones | I53: Autonomous Underwater Vehicles (AUVs) equipped with vision systems face unique challenges in real-time environmental perception due to harsh underwater conditions and computational constraints. This paper presents a novel cloud–edge framework for real-time vision–language analysis in underwater drones using the Qwen2.5-VL model. Our system employs a uniform frame sampling mechanism that balances temporal resolution with processing capabilities, achieving near real-time analysis at 1 fps from 23 fps input streams. We construct a comprehensive data flow model encompassing image enhancement, communication latency, cloud-side inference, and semantic result return, which is supported by a theoret… | J53: C | K53: Podvodni dronovi (nisu UAV) | L53: C
A54: 50 | B54: 2021 | C54: Effects of flooding stress on the saltmarsh halophyte Salicornia fruticosa (L.) L.: upscaling perspectives | D54: Research at the University of Copenhagen (University of Copenhagen) | E54: Coastal wetland ecosystem dynamics | F54: https://openalex.org/W4412282790 | H54: uav | I54: One of the major aftermaths of global warming is the ongoing global sea level rise, which is expected to seriously treat the worldwide coasts. Among coastal environments, saltmarshes are particularly sensitive to the increase of flooding and frequency of storm surges. Indeed, although saltmarshes respond with a sediment accretion and coastal niche shifting, sea rise rates and the coastal squeeze phenomenon jeopardize the acclimation capacity of saltmarsh species and plant communities. For these reasons, monitoring and studying the response of saltmarshes to flooding is crucial to understand the fate of these fragile ecosystems. For a comprehensive understanding of these processes, it is nece… | J54: A | K54: Slana močvara, UAV multispektralno | L54: A
A55: 51 | B55: 2025 | C55: Segmenting vegetation from UAV images via spectral reconstruction in complex field environments | D55: Plant Phenomics | E55: Remote Sensing in Agriculture | F55: https://openalex.org/W4408073201 | G55: https://doi.org/10.1016/j.plaphe.2025.100021 | H55: uav, unmanned aerial | I55: Segmentation of vegetation remote sensing images can minimize the interference of background, thus achieving efficient monitoring and analysis for vegetation information. The segmentation of vegetation poses a significant challenge due to the inherently complex environmental conditions. Currently, there is a growing trend of using spectral sensing combined with deep learning for field vegetation segmentation to cope with complex environments. However, two major constraints remain: the high cost of equipment required for field spectral data collection; the availability of field datasets is limited and data annotation is time-consuming and labor-intensive. To address these challenges, we propo… | J55: B | K55: Segmentacija vegetacije u poljoprivrednim poljima | L55: B
A56: 52 | B56: 2016 | C56: Multi-temporal UAV-borne LiDAR point clouds for vegetation analysis - a case study | D56: EGUGA | E56: Remote Sensing and LiDAR Applications | F56: https://openalex.org/W3020319779 | H56: uav | I56: (sažetak nije dostupan — otvoriti poveznicu) | J56: A | K56: Višekratni UAV LiDAR za analizu vegetacije | L56: A
A57: 53 | B57: 2024 | C57: Coastal transgressive dunefield evolution as a response to multi-decadal shoreline erosion | D57: Geomorphology | E57: Aeolian processes and effects | F57: https://openalex.org/W4393132234 | G57: https://doi.org/10.1016/j.geomorph.2024.109165 | H57: drone | I57: The Younghusband Peninsula coastal barrier extends ~190 km and is predominantly comprised of a mix of active, semi-stabilised and stabilised (relict) transgressive and parabolic dunefields. Wave driven shoreline erosion has triggered the rapid development of a transgressive dunefield along a portion the peninsula. This study focuses on a ~2 km region with the highest regional erosion rates (> −2.0 m/year since 1988), and which has experienced rapid destabilisation and subsequent landward translation of the dunefield. Aerial LIDAR derived datasets of the barrier system from 2008 and 2018 and eight drone photogrammetry surveys between August 2020 and April 2022 are used to compare the rates of… | J57: A | K57: Evolucija obalnih dina, dronska fotogrametrija | L57: A
A58: 54 | B58: 2025 | C58: Machine learning to detect, classify, and count blackbirds damaging agriculture using drone-based imagery: Supporting AI-driven automation for deployment of damage management tools | D58: Ecological Informatics | E58: UAV Applications and Optimization | F58: https://openalex.org/W4415653642 | G58: https://doi.org/10.1016/j.ecoinf.2025.103495 | H58: drone, drones | I58: As human populations expand and land use changes, human-wildlife conflicts are increasing, requiring cost-effective management tools that balance human well-being and wildlife conservation. Hazing devices are often used to mitigate conflicts between wildlife and agriculture with drones serving as both frightening devices and monitoring systems. Artificial intelligence (AI) enables automated detection, identification, and counting of wildlife, allowing for field-based Internet of Things (IoT) systems to selectively deploy tools when target species reach a critical threshold. We acquired drone imagery of mixed-species blackbird flocks – dominated by red-winged blackbirds (RWBL) Agelaius phoeni… | J58: A | K58: Ptice štetnice, sukob divljači i poljoprivrede, dronovi | L58: A
A59: 55 | B59: 2015 | C59: Classification of Ultra-High Resolution Orthophotos Combined with DSM Using a Dual Morphological Top Hat Profile | D59: Remote Sensing | E59: Advanced Image and Video Retrieval Techniques | F59: https://openalex.org/W2184116797 | G59: https://doi.org/10.3390/rs71215840 | H59: uav, uavs, unmanned aerial | I59: New aerial sensors and platforms (e.g., unmanned aerial vehicles (UAVs)) are capable of providing ultra-high resolution remote sensing data (less than a 30-cm ground sampling distance (GSD)). This type of data is an important source for interpreting sub-building level objects; however, it has not yet been explored. The large-scale differences of urban objects, the high spectral variability and the large perspective effect bring difficulties to the design of descriptive features. Therefore, features representing the spatial information of the objects are essential for dealing with the spectral ambiguity. In this paper, we proposed a dual morphology top-hat profile (DMTHP) using both morpholog… | J59: B | K59: Urbana klasifikacija ortofota | L59: B
A60: 56 | B60: 2025 | C60: Tree Species Classification Based on Point Cloud Completion | D60: Forests | E60: Remote Sensing and LiDAR Applications | F60: https://openalex.org/W4407193830 | G60: https://doi.org/10.3390/f16020280 | H60: uav | I60: LiDAR is an active remote sensing technology widely used in forestry applications, such as forest resource surveys, tree information collection, and ecosystem monitoring. However, due to the resolution limitations of 3D-laser scanners and the canopy occlusion in forest environments, the tree point clouds obtained often have missing data. This can reduce the accuracy of individual tree segmentation, which subsequently affects the tree species classification. To address the issue, this study used point cloud data with RGB information collected by the UAV platform to improve tree species classification by completing the missing point clouds. Furthermore, the study also explored the effects of p… | J60: A | K60: Klasifikacija vrsta drveća, UAV LiDAR | L60: A
A61: 57 | B61: 2020 | C61: Wildfire-Detection Method Using DenseNet and CycleGAN Data Augmentation-Based Remote Camera Imagery | D61: Remote Sensing | E61: Fire Detection and Safety Systems | F61: https://openalex.org/W3099352527 | G61: https://doi.org/10.3390/rs12223715 | H61: drone | I61: To minimize the damage caused by wildfires, a deep learning-based wildfire-detection technology that extracts features and patterns from surveillance camera images was developed. However, many studies related to wildfire-image classification based on deep learning have highlighted the problem of data imbalance between wildfire-image data and forest-image data. This data imbalance causes model performance degradation. In this study, wildfire images were generated using a cycle-consistent generative adversarial network (CycleGAN) to eliminate data imbalances. In addition, a densely-connected-convolutional-networks-based (DenseNet-based) framework was proposed and its performance was compared w… | J61: A | K61: Detekcija požara; dronske snimke | L61: A
A62: 58 | B62: 2024 | C62: Security, Privacy, and Trust Management on Decentralized Systems and Networks | D62: International Journal of Network Management | E62: Access Control and Trust | F62: https://openalex.org/W4403411766 | G62: https://doi.org/10.1002/nem.2311 | H62: uav, unmanned aerial | I62: With the rapid growth of size and scale in current organization, decentralize systems are becoming dominant, which is an interconnected information system where no single entity or central server is employed as a sole authority, such as Internet of Things (IoT), smart home system, smart city system, and more. For such systems, sensors are important to gather and process data as the lower level components. However, with the distributed deployment, decentralized systems are facing various security, privacy, and trust issues. For instance, any compromised sensor may leak sensitive data or be used to infect other entities within the system. It is also a long-term challenge to establish trust amo… | J62: C | K62: Sigurnost decentraliziranih mreža | L62: C
A63: 59 | B63: 2025 | C63: A Federated Learning Framework for Enhanced Data Security and Cyber Intrusion Detection in Distributed Network of Underwater Drones | D63: IEEE Access | E63: Underwater Vehicles and Communication Systems | F63: https://openalex.org/W4406457581 | G63: https://doi.org/10.1109/access.2025.3530499 | H63: drone, drones | I63: Underwater drones are vital for scientific research, environmental monitoring, and maritime operations, allowing data collection in challenging environments. However, their deployment faces issues such as low bandwidth, high latency, signal attenuation, and intermittent connectivity due to mobility and water currents. Traditional centralized data processing approaches are inefficient under these conditions as they require transmitting large volumes of raw data to a central location. To address these challenges, this study proposes a Federated Learning (FL) framework specifically tailored for underwater networks. Unlike centralized approaches, FL enables underwater drones to collaboratively t… | J63: C | K63: Podvodni dronovi | L63: C
A64: 60 | B64: 2023 | C64: The Development of Drone Techology and its Regulation in the European Union | D64: EU agrarian Law | E64: International Law and Aviation | F64: https://openalex.org/W4390202040 | G64: https://doi.org/10.2478/eual-2023-0005 | H64: drone, drones, uavs, unmanned aerial, unmanned aircraft | I64: Abstract Unmanned Aerial Vehicles (UAVs), or drones, have rapidly transformed from niche gadgets to versatile tools with widespread applications across various sectors. This paper investigates the regulatory landscape of drones within the European Union (EU) and its intricate balance between fostering technological innovation and addressing safety, privacy, security, and environmental concerns. Drones’ exponential growth in Europe’s airspace has prompted the EU to establish a legal framework that addresses their multifaceted implications. While drones offer unprecedented opportunities in areas like disaster response and remote sensing, they also pose challenges such as airspace congestion, p… | J64: C | K64: Regulativa dronova u EU (bez okolišne primjene) | L64: C
A65: 61 | B65: 2025 | C65: Field heterogeneity of soil texture controls leaf water potential spatial distribution predicted from UAS-based vegetation indices in non-irrigated vineyards | D65: Biogeosciences | E65: Horticultural and Viticultural Research | F65: https://openalex.org/W4406930131 | G65: https://doi.org/10.5194/bg-22-513-2025 | H65: uas | I65: Abstract. Grapevine water status exhibits substantial variability even within a single vineyard. Understanding how edaphic, topographic, and climatic conditions impact grapevine water status heterogeneity at the field scale, in non-irrigated vineyards, is essential for winemakers as it significantly influences wine quality. This study aimed to quantify the spatial distribution of grapevine leaf water potential (Ψleaf) within vineyards and to assess the influence of soil property heterogeneity, topography, and climatic conditions on intra-field variability in two non-irrigated vineyards during two viticultural seasons. By combining multilinear vegetation indices from very-high-spatial-resolut… | J65: B | K65: Vinogradi, vodni status | L65: B
A66: 62 | B66: 2024 | C66: UAV Mapping for Flood Routing in Steep and Densely Vegetated Areas: Insights from the Contok River Basin, Garang Watershed, Indonesia | D66: Limnotek perairan darat tropis di Indonesia | E66: Remote Sensing and LiDAR Applications | F66: https://openalex.org/W4400466935 | G66: https://doi.org/10.55981/limnotek.2024.5028 | H66: uav, unmanned aerial | I66: This research utilizes photogrammetry to assess flood routing dynamics in the Contok river basin, a sub-watershed with a challenging landscape characterized by steep slopes, dense vegetation, and meandering patterns. The objectives are to assess Unmanned Aerial Vehicle (UAV) mapping accuracy, evaluate the river's capacity for design flood volumes, quantify the impact of land cover changes on surface runoff, and provide insights for early warning systems and watershed conservation strategies. The study area, encompassing the Contok River Basin, a sub-watershed of the Garang Watershed, covers 7,413 km² and includes a stream length of 5,274 meters in Semarang City, Central Java, Indonesia. This… | J66: B | K66: UAV kartiranje za usmjeravanje poplava (hidrologija) | L66: B
A67: 63 | B67: 2021 | C67: A deep 2D/3D Feature-Level fusion for classification of UAV multispectral imagery in urban areas | D67: Geocarto International | E67: Remote-Sensing Image Classification | F67: https://openalex.org/W3185991925 | G67: https://doi.org/10.1080/10106049.2021.1959655 | H67: uav, unmanned aerial | I67: In this paper, a deep convolutional neural network (CNN) is developed to classify the Unmanned Aerial Vehicle (UAV) derived multispectral imagery and normalized digital surface model (DSM) data in urban areas. For this purpose, a multi-input deep CNN (MIDCNN) architecture is designed using 11 parallel CNNs; 10 deep CNNs to extract the features from all possible triple combinations of spectral bands as well as one deep CNN dedicated to the normalized DSM data. The proposed method is compared with the traditional single-input (SI) and double-input (DI) deep CNN designations and random forest (RF) classifier, and evaluated using two independent test datasets. The results indicate that increasin… | J67: B | K67: Urbana klasifikacija UAV multispektralnih snimaka | L67: B
A68: 64 | B68: 2025 | C68: Aerial imaging for early assessment of yield potential in maize | D68: Revista CERES | E68: Remote Sensing in Agriculture | F68: https://openalex.org/W7162289624 | G68: https://doi.org/10.71252/2177-34912025720038 | H68: unmanned aerial | I68: The use of unmanned aerial vehicles imagery has become an established practice in high-throughput phenotyping for predicting the yield potential of maize (Zea mays L.), although applying these technologies presents challenges due to regional specificities. This study aimed to assess the effectiveness of RGB (red, green, and blue) aerial imagery for the early identification of yield maize genotypes during the vegetative stage. Four genotypes were evaluated using a randomized block design with four replications. The experiment involved seven flights at two heights. Twenty-nine RGB vegetation indices were derived from image processing to discriminate genotypes based on plot-level grain yield. N… | J68: B | K68: Prinos kukuruza | L68: B
A69: 65 | B69: 2020 | C69: Drones Used to Calibrate Equipment to Monitor Coastal Currents | D69: ODU Digital Commons (Old Dominion University) | E69: Coastal and Marine Dynamics | F69: https://openalex.org/W3109768354 | H69: drones | I69: (sažetak nije dostupan — otvoriti poveznicu) | J69: A | K69: Dronovi za kalibraciju mjerenja obalnih struja | L69: A
A70: 66 | B70: 2023 | C70: Drone Observation for the Quantitative Study of Complex Multilevel Societies | D70: Animals | E70: Wildlife Ecology and Conservation | F70: https://openalex.org/W4380051706 | G70: https://doi.org/10.3390/ani13121911 | H70: drone, drones, unmanned aerial | I70: Unmanned aerial vehicles (drones) have recently been used in various behavioral ecology studies. However, their application has been limited to single groups, and most studies have not implemented individual identification. A multilevel society refers to a social structure in which small stable "core units" gather and make a larger, multiple-unit group. Here, we introduce recent applications of drone technology and individual identification to complex social structures involving multiple groups, such as multilevel societies. Drones made it possible to obtain the identification, accurate positioning, or movement of more than a hundred individuals in a multilevel social group. In addition, in … | J70: A | K70: Dronsko promatranje višerazinskih društava životinja | L70: A
A71: 67 | B71: 2023 | C71: Estimation of tomato water status with photochemical reflectance index and machine learning: Assessment from proximal sensors and UAV imagery | D71: Frontiers in Plant Science | E71: Remote Sensing in Agriculture | F71: https://openalex.org/W4362671667 | G71: https://doi.org/10.3389/fpls.2023.1057733 | H71: uav, unmanned aerial | I71: Tracking plant water status is a critical step towards the adaptive precision irrigation management of processing tomatoes, one of the most important specialty crops in California. The photochemical reflectance index (PRI) from proximal sensors and the high-resolution unmanned aerial vehicle (UAV) imagery provide an opportunity to monitor the crop water status efficiently. Based on data from an experimental tomato field with intensive aerial and plant-based measurements, we developed random forest machine learning regression models to estimate tomato stem water potential (ψstem), (using observations from proximal sensors and 12-band UAV imagery, respectively, along with weather data. The pro… | J71: B | K71: Rajčica, vodni status | L71: B
A72: 68 | B72: 2021 | C72: Development of the Artificial Intelligence and Optical Sensing Methods for Oil Pollution Monitoring of the Sea by Drones | D72: Applied Sciences | E72: Oil Spill Detection and Mitigation | F72: https://openalex.org/W3154927784 | G72: https://doi.org/10.3390/app11083642 | H72: drone, drones | I72: The oil pollution of seas is increasing, especially in local areas, such as ports, roadsteads of the vessels, and bunkering zones. Today, methods of monitoring seawater are costly and applicable only in the case of big ecology disasters. The development of an operative and reasonable project for monitoring the sea surface for oil slick detection is described in this article using drones equipped with optical sensing and artificial intelligence. The monitoring system is implemented in the form of separate hard and soft frameworks (HSFWs) that combine monitoring methods, hardware, and software. Three frameworks are combined to fulfill the entire monitoring mission. HSFW1 performs the function … | J72: A | K72: Onečišćenje mora naftom, dronovi | L72: A
A73: 69 | B73: 2020 | C73: Integration of Multi-Sensor Data to Estimate Plot-Level Stem Volume Using Machine Learning Algorithms–Case Study of Evergreen Conifer Planted Forests in Japan | D73: Remote Sensing | E73: Remote Sensing and LiDAR Applications | F73: https://openalex.org/W3027505569 | G73: https://doi.org/10.3390/rs12101649 | H73: uas, unmanned aerial | I73: The development of new methods for estimating precise forest structure parameters is essential for the quantitative evaluation of forest resources. Conventional use of satellite image data, increasing use of terrestrial laser scanning (TLS), and emerging trends in the use of unmanned aerial systems (UASs) highlight the importance of modern technologies in the realm of forest observation. Each technology has different advantages, and this work seeks to incorporate multiple satellite, TLS- and UAS-based remote sensing data sets to improve the ability to estimate forest structure parameters. In this paper, two regression analysis approaches are considered for the estimation: random forest regre… | J73: A | K73: Volumen sastojine, UAS | L73: A
A74: 70 | B74: 2025 | C74: Potential of Drones for Avian Ecological Monitoring in West African Mangrove Ecosystems | D74: Open Journal of Ecology | E74: UAV Applications and Optimization | F74: https://openalex.org/W4409705460 | G74: https://doi.org/10.4236/oje.2025.154020 | H74: drone, drones | I74: Bouche du Roy, a community mangrove ecosystem in the RAMSAR 1017 site in Benin, is important for bird conservation. However, it faces many anthropogenic threats. Conservation efforts have been made since its inception, but managers face major constraints. Ecological monitoring is costly and material resources are constantly in short supply, making repeated operations difficult. Recently, drone technology has emerged as an effective tool for wildlife monitoring, particularly in inaccessible areas. The aim of this study was to assess the potential of drones for ecological monitoring of avian biodiversity in the mangrove ecosystems of the Bouche du Roy in Benin. In order to maximize the chances… | J74: A | K74: Ptice u mangrovama, dronovi | L74: A
A75: 71 | B75: 2016 | C75: Method for NIR Reflectance Estimation with Visible Camera Data based on Regression for NDVI Estimation and its Application for Insect Damage Detection of Rice Paddy Fields | D75: INTERNATIONAL JOURNAL OF ADVANCED RESEARCH IN ARTIFICIAL INTELLIGENCE | E75: Remote Sensing in Agriculture | F75: https://openalex.org/W2567061793 | G75: https://doi.org/10.14569/ijarai.2016.051103 | H75: drone | I75: Method for Near Infrared: NIR reflectance estimation with visible camera data based on regression for Normalized Vegetation Index: NDVI estimation is proposed together with its application for insect damage detection of rice paddy fields. Through experiments at rice paddy fields which is situated at Saga Prefectural Agriculture Research Institute SPARI in Saga city, Kyushu, Japan, it is found that there is high correlation between NIR reflectance and Green color reflectance. Therefore, it is possible to estimate NIR reflectance with visible camera data which results in possibility of estimation of NDVI with drone mounted visible camera data. As is well known that the protein content in rice … | J75: B | K75: NDVI riže, dron s kamerom | L75: B
A76: 72 | B76: 2022 | C76: Drone imagery forest fire detection and classification using modified deep learning model | D76: Thermal Science | E76: Fire Detection and Safety Systems | F76: https://openalex.org/W4317422903 | G76: https://doi.org/10.2298/tsci22s1411m | H76: drone, drones, uav, unmanned aerial | I76: With the progression of information technologies, unmanned aerial vehicles (UAV) or drones are more significant in remote monitoring the environment. One main application of UAV technology relevant to nature monitoring is monitoring wild animals. Among several natural disasters, Wildfires are one of the deadliest and cause damage to millions of hectares of forest lands or resources which threatens the lives of animals and people. Drones present novel features and convenience which include rapid deployment, adjustable and wider viewpoints, less human intervention, and high maneuverability. With the effective enforcement of deep learning in many applications, it is used in the domain of forest… | J76: A | K76: Detekcija šumskih požara dronskim snimkama | L76: A
A77: 73 | B77: 2025 | C77: Unlocking Hyper-Resolution Dynamics: Multi-GNSS Aided UAV-LiDAR for Earth Surface Evolution | D77: Zenodo (CERN European Organization for Nuclear Research) | E77: 3D Surveying and Cultural Heritage | F77: https://openalex.org/W7107866176 | G77: https://doi.org/10.5281/zenodo.17729806 | H77: uav, unmanned aerial | I77: The Earth's surface is a dynamic interface, constantly evolving under the influence of natural processes and anthropogenic activities. Monitoring these changes with high spatial and temporal resolution is crucial for understanding geomorphological processes, assessing hazards, and managing natural resources. Traditional surveying methods often lack the spatial density and efficiency required to capture the complex, hyper-resolution dynamics inherent in many geomorphic phenomena. Unmanned Aerial Vehicle (UAV) borne Light Detection and Ranging (LiDAR) has emerged as a transformative technology, offering unprecedented detail in topographic mapping. However, the absolute accuracy of UAV-LiDAR sy… | J77: B | K77: UAV LiDAR za geomorfološke promjene | L77: B
A78: 74 | B78: 2024 | C78: AI-based Precision Enhancement for Change Detection in Drone/UAV Videos | D78: International Journal for Research in Applied Science and Engineering Technology | E78: Remote Sensing and Land Use | F78: https://openalex.org/W4399540446 | G78: https://doi.org/10.22214/ijraset.2024.63189 | H78: drone, uav | I78: The rapid advancement in drone/UAV technology has led to their extensive use in various domains including surveillance, agriculture, and environmental monitoring. Change detection in UAV videos is crucial for identifying significant alterations in the observed areas. However, challenges such as varying scales, resolutions, and orientations of video frames pose significant hurdles. This paper addresses these challenges by leveraging the SIFT algorithm for panoramic stitching and change detection, followed by the application of the YOLOv8 model for high-precision anomaly detection | J78: B | K78: Detekcija promjena u UAV videu (generičko) | L78: B
A79: 75 | B79: 2021 | C79: (bez naslova) | D79: KTH Publication Database DiVA (KTH Royal Institute of Technology) | E79: Robotic Path Planning Algorithms | F79: https://openalex.org/W3201403862 | G79: https://doi.org/10.3390/electronics10182218 | H79: drones, unmanned aerial | I79: Unmanned aerial vehicles or drones are becoming one of the key machines/tools of the modern world, particularly in military applications. Numerous research works are underway to explore the possibility of using these machines in other applications such as parcel delivery, construction work, hurricane hunting, 3D mapping, protecting wildlife, agricultural activities, search and rescue, etc. Since these machines are unmanned vehicles, their functionality is completely dependent upon the performance of their control system. This paper presents a comprehensive approach for dynamic modeling, control system design, simulation and optimization of a quadcopter. The main objective is to study the beh… | J79: C | K79: Generički pregled dronova (vojne primjene) | L79: C
A80: 76 | B80: 2020 | C80: EVALUATING A CONVOLUTIONAL NEURAL NETWORK FOR FEATURE EXTRACTION AND TREE SPECIES CLASSIFICATION USING UAV-HYPERSPECTRAL IMAGES | D80: ISPRS annals of the photogrammetry, remote sensing and spatial information sciences | E80: Remote Sensing in Agriculture | F80: https://openalex.org/W3047190055 | G80: https://doi.org/10.5194/isprs-annals-v-3-2020-193-2020 | H80: uav, uavs, unmanned aerial | I80: Abstract. The classification of tree species can significantly benefit from high spatial and spectral information acquired by unmanned aerial vehicles (UAVs) associated with advanced feature extraction and classification methods. Different from the traditional feature extraction methods, that highly depend on user’s knowledge, the convolutional neural network (CNN)-based method can automatically learn and extract the spatial-related features layer by layer. However, in order to capture significant features of the data, the CNN classifier requires a large number of training samples, which are hardly available when dealing with tree species in tropical forests. This study investigated the foll… | J80: A | K80: Klasifikacija vrsta drveća, UAV hiperspektralno | L80: A
A81: 77 | B81: 2023 | C81: A cooperative scheme for late leaf spot estimation in peanut using UAV multispectral images | D81: PLoS ONE | E81: Remote Sensing in Agriculture | F81: https://openalex.org/W4360997749 | G81: https://doi.org/10.1371/journal.pone.0282486 | H81: uav, uavs, unmanned aerial | I81: In Australia, peanuts are mainly grown in Queensland with tropical and subtropical climates. The most common foliar disease that poses a severe threat to quality peanut production is late leaf spot (LLS). Unmanned aerial vehicles (UAVs) have been widely investigated for various plant trait estimations. The existing works on UAV-based remote sensing have achieved promising results for crop disease estimation using a mean or a threshold value to represent the plot-level image data, but these methods might be insufficient to capture the distribution of pixels within a plot. This study proposes two new methods, namely measurement index (MI) and coefficient of variation (CV), for LLS disease esti… | J81: B | K81: Bolest kikirikija | L81: B
... A85: 81 | B85: 2020 | C85: Crop Separability from Individual and Combined Airborne Imaging Spectroscopy and UAV Multispectral Data | D85: Remote Sensing | E85: Remote Sensing in Agriculture | F85: https://openalex.org/W3017100647 | G85: https://doi.org/10.3390/rs12081256 | H85: uav, unmanned aerial | I85: Crop species separation is essential for a wide range of agricultural applications—in particular, when seasonal information is needed. In general, remote sensing can provide such information with high accuracy, but in small structured agricultural areas, very high spatial resolution data (VHR) are required. We present a study involving spectral and textural features derived from near-infrared (NIR) Red Green Blue (NIR-RGB) band datasets, acquired using an unmanned aerial vehicle (UAV), and an imaging spectroscopy (IS) dataset acquired by the Airborne Prism EXperiment (APEX). Both the single usage and combination of these datasets were analyzed using a random forest-based method for crop sepa… | J85: B | K85: Razdvajanje usjeva | L85: B
A86: 82 | B86: 2011 | C86: UAV operated Hyperspectral Imager for forest and agriculture applications | E86: Infrared Target Detection Methodologies | F86: https://openalex.org/W2970191788 | H86: uav | I86: (sažetak nije dostupan — otvoriti poveznicu) | J86: B | K86: Hiperspektralni senzor za šume i poljoprivredu (instrument) | L86: B
A87: 83 | B87: 2016 | C87: Flooding scenarios due to land subsidence and sea‐level rise: a case study for Lipari Island (Italy) | D87: Terra Nova | E87: Maritime and Coastal Archaeology | F87: https://openalex.org/W2552574646 | G87: https://doi.org/10.1111/ter.12246 | H87: uav, unmanned aerial | I87: Abstract Archaeological and instrumental data indicate that the southern sector of the volcanic island of Lipari has been subsiding for the last 2100 years due to isostatic and tectonic factors, at variable rates of up to ~11 mm a−1. Based on this data, a detailed marine flooding scenario for 2100 AD is provided for the bay of Marina Lunga in the eastern part of the island from (1) an ultra‐high‐resolution Digital Terrain and Marine Model (DTMM) generated from multibeam bathymetry (MB) and Unmanned Aerial Vehicles (UAV), (2) the rate of land subsidence from Global Positioning System (GPS) data and (3) the regional sea‐level projections of the International Panel on Climate Change (IPCC). Whe… | J87: B | K87: Scenariji poplavljivanja otoka, UAV DTM | L87: B
A88: 84 | B88: 2019 | C88: UAV and Ground Image-Based Phenotyping: A Proof of Concept with Durum Wheat | D88: Remote Sensing | E88: Remote Sensing in Agriculture | F88: https://openalex.org/W2947572107 | G88: https://doi.org/10.3390/rs11101244 | H88: uav, unmanned aerial | I88: Climate change is one of the primary culprits behind the restraint in the increase of cereal crop yields. In order to address its effects, effort has been focused on understanding the interaction between genotypic performance and the environment. Recent advances in unmanned aerial vehicles (UAV) have enabled the assembly of imaging sensors into precision aerial phenotyping platforms, so that a large number of plots can be screened effectively and rapidly. However, ground evaluations may still be an alternative in terms of cost and resolution. We compared the performance of red–green–blue (RGB), multispectral, and thermal data of individual plots captured from the ground and taken from a UAV,… | J88: B | K88: Fenotipizacija durum pšenice | L88: B
A89: 85 | B89: 2024 | C89: Pemanfaatan Peta Foto Tegak Sebagai Peta Dasar Untuk Evaluasi Pelaksanaan Rencana Tata Ruang | D89: Urban and Regional Studies Journal | E89: 3D Modeling in Geospatial Applications | F89: https://openalex.org/W4406398766 | G89: https://doi.org/10.35965/ursj.v7i1.5272 | H89: unmanned aerial | I89: Tujuan dari penelitian ini adalah melakukan evaluasi Rencana Tata Ruang (RTR) pada potensi adanya ketidaksesuaian pola ruang terhadap existing keadaan di lapangan, sehingga lokasi penelitian yang dipilih terletak pada daerah yang memiliki kemungkinan terdapat pembangunan yang signifikan untuk mendeteksi kecocokan pemanfaatan ruang dan di wilayah yang relative sama atau sedikit pembangunan untuk evaluasi penyusunan pemanfaatan tanah sesuai pola ruang. Penelitian dilakukan di 2 wilayah administrasi Kelurahan/Desa yang keduanya berada di Kecamatan Barru, Kabupaten Barru. Area pertama adalah Kelurah Coppo yang berada di Kecamatan Barru Kabuopaten Barru. Hasil dari Penelitian ini menunjukan bahwa… | J89: C | K89: Prostorno planiranje (Indonezija) | L89: C
A90: 86 | B90: 2020 | C90: Geovisualization of the Excavation Process in the Lesvos Petrified Forest, Greece Using Augmented Reality | D90: ISPRS International Journal of Geo-Information | E90: 3D Surveying and Cultural Heritage | F90: https://openalex.org/W3033669335 | G90: https://doi.org/10.3390/ijgi9060374 | H90: unmanned aerial | I90: Augmented reality (AR), in conjunction with 3D geovisualization methods, can provide significant support in monitoring geoconservation activities in protected geosites, such as the excavation process in fossil sites. The excavation process requires a monitoring methodology that will provide a complete and accurate overview of the fossils, their dimensions, and location within the different pyroclastic horizons, and the progress of the excavation works. The main purpose of this paper is the development of a user-friendly augmented map application, specifically designed for tracking the position of petrified tree trunks, providing information for their geometric features, and mapping the spati… | J90: B | K90: Geokonzervacija iskopa, UAS za snimanje | L90: B
A91: 87 | B91: 2024 | C91: A hybrid search and model-based approach for testing the self-adaptive unmanned aircraft system software | D91: Computer Standards & Interfaces | E91: Software Testing and Debugging Techniques | F91: https://openalex.org/W4405220677 | G91: https://doi.org/10.1016/j.csi.2024.103959 | H91: unmanned aircraft | I91: (sažetak nije dostupan — otvoriti poveznicu) | J91: C | K91: Testiranje softvera UAS-a | L91: C
A92: 88 | B92: 2024 | C92: Individual tree detection and segmentation from unmanned aerial vehicle-LiDAR data based on a trunk point distribution indicator | D92: Computers and Electronics in Agriculture | E92: Remote Sensing and LiDAR Applications | F92: https://openalex.org/W4391714923 | G92: https://doi.org/10.1016/j.compag.2024.108717 | H92: unmanned aerial | I92: (sažetak nije dostupan — otvoriti poveznicu) | J92: A | K92: Detekcija pojedinačnih stabala UAV LiDAR | L92: A
A93: 89 | B93: 2022 | C93: Validation of Rapid and Low-Cost Approach for the Delineation of Zone Management Based on Machine Learning Algorithms | D93: Agronomy | E93: Soil Geostatistics and Mapping | F93: https://openalex.org/W4206468308 | G93: https://doi.org/10.3390/agronomy12010183 | H93: uav, unmanned aerial | I93: Proximal soil sensors are receiving strong attention from several disciplinary fields, and this has led to a rise in their availability in the market in the last two decades. The aim of this work was to validate agronomically a zone management delineation procedure from electromagnetic induction (EMI) maps applied to two different rainfed durum wheat fields. The k-means algorithm was applied based on the gap statistic index for the identification of the optimal number of management zones and their positions. Traditional statistical analysis was performed to detect significant differences in soil characteristics and crop response of each management zones. The procedure showed the presence of … | J93: B | K93: Zone upravljanja tlom, pšenica | L93: B
A94: 90 | B94: 2023 | C94: Neural Radiation Fields in a Tidal Flat Environment | D94: Applied Sciences | E94: Computer Graphics and Visualization Techniques | F94: https://openalex.org/W4387234632 | G94: https://doi.org/10.3390/app131910848 | H94: uavs, unmanned aerial | I94: Tidal flats are critical ecosystems, playing a vital role in biodiversity conservation and ecological balance. Collecting tidal flat environmental information using unmanned aerial vehicles (UAVs) and subsequently utilizing 3D reconstruction techniques for their detection and protection holds significance in providing comprehensive and detailed tidal flat information, including terrain, slope, and other parameters. It also enables scientific decision-making for the preservation of tidal flat ecosystems and the monitoring of factors such as rising sea levels. Moreover, the latest advancements in neural radiance fields (Nerf) have provided valuable insights and novel perspectives for our work.… | J94: A | K94: Plimne ravnice, UAV 3D rekonstrukcija | L94: A
A95: 91 | B95: 2018 | C95: Environmental Monitoring System by Using Unmanned Aerial Vehicle | D95: Network Protocols and Algorithms | E95: Water Quality Monitoring Technologies | F95: https://openalex.org/W2791679594 | G95: https://doi.org/10.5296/npa.v9i3-4.12021 | H95: uav, unmanned aerial | I95: This paper presents a reliable and low cost environmental monitoring system. The system uses an Unmanned Ariel Vehicle (UAV) equipped with a set of sensors, microcontroller, wireless system, and other accessories. The system consists of two systems namely air quality monitoring system and water quality monitoring system. The air quality monitoring system consists of a set of gas sensors and microcontroller. This system measures the concentration of greenhouse gases at different altitudes under different environmental conditions. On the other hand, the water quality monitoring system consists of a set of water quality sensors, microcontroller, and water sampling unit. This system collects wat… | J95: A | K95: UAV sustav za praćenje zraka i vode | L95: A
A96: 92 | B96: 2023 | C96: UAV Inventory of the Last Remaining Dragon Tree Forest on Earth | D96: Forests | E96: Pharmacological Effects of Medicinal Plants | F96: https://openalex.org/W4363647848 | G96: https://doi.org/10.3390/f14040766 | H96: drone, drones, uav, uavs, unmanned aerial | I96: The last remaining Dragon Tree Forest on Earth survives on a small plateau (Roqeb di Firmihin) in Socotra Island (Yemen). The Socotran Dragon’s Blood Tree (Dracaena cinnabari Balf. f.) is endemic to the Socotra Archipelago UNESCO World Heritage Site. Being a culturally important and endangered tree species, its conservation is a priority. Despite this, a complete inventory of the Firmihin Dracaena forest (14.9 km2) has never been attempted before. We applied the use of unmanned aerial vehicles (UAVs) for the first time in conserving the Socotran Dragon’s Blood Tree. A pair of UAVs (small drones) were used during field surveys in 2021 to spatially describe individual tree positions, tree dens… | J96: A | K96: Inventura šume zmajeva stabla | L96: A
A97: 93 | B97: 2024 | C97: Development of a Seafloor Litter Database and Application of Image Preprocessing Techniques for UAV-Based Detection of Seafloor Objects | D97: Electronics | E97: Underwater Acoustics Research | F97: https://openalex.org/W4402279098 | G97: https://doi.org/10.3390/electronics13173524 | H97: uav, uavs, unmanned aerial | I97: Marine litter poses a significant global threat to marine ecosystems, primarily driven by poor waste management, inadequate infrastructure, and irresponsible human activities. This research investigates the application of image preprocessing techniques and deep learning algorithms for the detection of seafloor objects, specifically marine debris, using unmanned aerial vehicles (UAVs). The primary objective is to develop non-invasive methods for detecting marine litter to mitigate environmental impacts and support the health of marine ecosystems. Data was collected remotely via UAVs, resulting in a novel database of over 5000 images and 12,000 objects categorized into 31 classes, with metadat… | J97: A | K97: Morski otpad, UAV detekcija | L97: A
A98: 94 | B98: 2023 | C98: Measurement of near-coastal wind field characteristics based on UAV | D98: Measurement | E98: Aerospace Engineering and Energy Systems | F98: https://openalex.org/W4386625229 | G98: https://doi.org/10.1016/j.measurement.2023.113550 | H98: uav | I98: (sažetak nije dostupan — otvoriti poveznicu) | J98: B | K98: Obalno polje vjetra mjereno UAV-om (meteorologija) | L98: B
... A102: 98 | B102: 2018 | C102: The use of secondary resource potential of pharmaceutical waste from glass in the pr duction of ceramic tiles | D102: Bulletin of the National Technical University «KhPI» Series New solutions in modern technologies | E102: Medical and Pharmaceutic Studies | F102: https://openalex.org/W2898890266 | G102: https://doi.org/10.20998/2413-4295.2018.26.38 | H102: uas | I102: The article describes ecological aspects of pharmaceutical glass wastes. It is determined that the greatest negative impact on the environment components has wastes containing pharmaceutical residue. It was analyzed that pharmaceutical glass wastes mainly consist of used ampoules (UAs).The ecological necessity of taking away and disposing residues of pharmaceutical substances from UAs by their disposal is determined. The resource possibilities of using UAs as the secondary material in production of ceramic tiles is analyzed. Monitoring of the formation and accumulation of a mixture of ampoules in the therapeutic hospital department was carried out. The mixture consisted of ampoules containin… | J102: C | K102: „UAs“ = used ampoules | L102: C
A103: 99 | B103: 2023 | C103: ICTを活用した野生鳥獣の生態調査技術の開発 | D103: Institutional Repositories DataBase (IRDB) | E103: Financial Crisis of the 21st Century | F103: https://openalex.org/W7144515362 | H103: drone, drones | I103: Recently, research on solving regional problems through industry-academia-government collaboration has been\npromoted in Sanyo-Onoda city area. As part of this research, through a proposal from Mr. Nakamura of West Japan Jibie Farm, a study on "Countermeasures against wildlife damage using drones and ICT," was started from April 2020. Thetemporal goal of the research was defined to be "ecological survey of wild boars utilizing ICT", i.e. (1) survey of traces ofwild boar inhabitation by actually exploring the mountain area, (2) the development of remote observation technology of wild boars at Wallows and Beast Roads discovered by reconnaissance, and (3) the development of infrared photography… | J103: A | K103: Ekološki popis divljih svinja dronovima | L103: A
A104: 100 | B104: 2024 | C104: Enhanced Estimation of Rice Leaf Nitrogen Content via the Integration of Hybrid Preferred Features and Deep Learning Methodologies | D104: Agronomy | E104: Remote Sensing in Agriculture | F104: https://openalex.org/W4399494733 | G104: https://doi.org/10.3390/agronomy14061248 | H104: uav, unmanned aerial | I104: Efficiently obtaining leaf nitrogen content (LNC) in rice to monitor the nutritional health status is crucial in achieving precision fertilization on demand. Unmanned aerial vehicle (UAV)-based hyperspectral technology is an important tool for determining LNC. However, the intricate coupling between spectral information and nitrogen remains elusive. To address this, this study proposed an estimation method for LNC that integrates hybrid preferred features with deep learning modeling algorithms based on UAV hyperspectral imagery. The proposed approach leverages XGBoost, Pearson correlation coefficient (PCC), and a synergistic combination of both to identify the characteristic variables for LN… | J104: B | K104: Dušik u riži, UAV hiperspektralno | L104: B

Sheet Uzorak_50_rano
A1: Uzorak B: 50 slučajnih zapisa, 2005.–2015. (seed 20260827)
A2: Žuti stupac = KONAČNA OCJENA (A/B/C), popunite ili potvrdite; prijedlog (AI) je samo pomoć.
A4: # | B4: Godina | C4: Naslov | D4: Časopis / izvor | E4: OpenAlex tema | F4: OpenAlex ID (poveznica) | G4: DOI | H4: UAV pojam | I4: Sažetak (skraćen) | J4: Prijedlog (AI) | K4: Obrazloženje prijedloga | L4: KONAČNA OCJENA | M4: Napomena ocjenjivača
A5: 1 | B5: 2006 | C5: Szendro - type Integrated Vegetation Fire Management--Wildfire Management Program from Hungary | E5: Fire effects on ecosystems | F5: https://openalex.org/W1902224079 | H5: uav | I5: Szendrő Fire Department is located in the northeastern part of Hungary. The main task is to fight against wildfire and mitigate the impact of fire at the Aggtelek National Park -- which belongs to the UNESCO World Heritage list. Because of greater effectiveness, in 2004 the Fire Department started a project named Integrated Vegetation Fire Management (IVFM). The IVFM consist of two main parts: Peripheries and Modules. The land use planning, finance, public relations, education, media connections, protective equipment belongs to Peripheries. The Modules are: Tower based environment monitoring and fire detection system, Mobile command control unit and Static and dynamic decision support system… | J5: A | K5: Upravljanje požarima, UAV izviđanje | L5: A
A6: 2 | B6: 2014 | C6: A Probabilistic Gas Patch Path Prediction Approach for Airborne Gas Source Localization in Non-Uniform Wind Fields | D6: Sensor Letters | E6: Insect Pheromone Research and Control | F6: https://openalex.org/W1986490556 | G6: https://doi.org/10.1166/sl.2014.3168 | H6: uav, unmanned aerial | I6: filter In this paper, we show that a micro unmanned aerial vehicle (UAV) equipped with commercially available gas sensors can address environmental monitoring and gas source localization (GSL) tasks. To account for the challenges of gas sensing under real-world conditions, we present a probabilistic approach for GSL that is based on a particle filter (PF). Simulation and real-world experiments demonstrate the suitability of this algorithm for micro UAV platforms. | J6: A | K6: Lokalizacija izvora plina mikro-UAV-om (okolišni monitoring) | L6: A
A7: 3 | B7: 2015 | C7: Approaching birds with drones: first experiments and ethical guidelines | D7: Biology Letters | E7: Wildlife-Road Interactions and Conservation | F7: https://openalex.org/W2111664716 | G7: https://doi.org/10.1098/rsbl.2014.0754 | H7: drone, drones, unmanned aerial | I7: Unmanned aerial vehicles, commonly called drones, are being increasingly used in ecological research, in particular to approach sensitive wildlife in inaccessible areas. Impact studies leading to recommendations for best practices are urgently needed. We tested the impact of drone colour, speed and flight angle on the behavioural responses of mallards Anas platyrhynchos in a semi-captive situation, and of wild flamingos (Phoenicopterus roseus) and common greenshanks (Tringa nebularia) in a wetland area. We performed 204 approach flights with a quadricopter drone, and during 80% of those we could approach unaffected birds to within 4 m. Approach speed, drone colour and repeated flights had no… | J7: A | K7: Prilaz pticama dronovima, etičke smjernice | L7: A
A8: 4 | B8: 2015 | C8: Ecological Benefits Evaluation in Ecological Migration Zone Based on Ecological Green Equivalent: A Case Study of Migration Zone in Yanchi County | D8: 亚洲农业研究：英文版 | E8: Land Use and Ecosystem Services | F8: https://openalex.org/W3142025330 | H8: uav | I8: With four ecological migration zones in Huamachi Town of Yanchi County in Ningxia Autonomous Region as the object of study,we carry out the evaluation of ecological benefits in ecological migration zone. Using the SPOT satellite remote sensing image in 2008 and UAV aerophotographic image in 2013,we first monitor and analyze the land use change over five years in the study area,and then adopt ecological green equivalent evaluation model for the evaluation of ecological benefits in the ecological migration zone. Studies have shown that:( i) from 2008 to 2013,the ecological green equivalent in the study area was increased and the ecological environment was improved;( ii) the ecological green eq… | J8: A | K8: Promjena uporabe zemljišta, UAV snimke | L8: A
A9: 5 | B9: 2007 | C9: Feature identification from commercial satellite images for military and homeland security operations in coastal zones | D9: Journal of Applied Remote Sensing | E9: Maritime and Coastal Archaeology | F9: https://openalex.org/W2121895676 | G9: https://doi.org/10.1117/1.2722339 | H9: unmanned aerial | I9: Supporting U.S. military operations and homeland security requirements in and around coastal zones, geospatial intelligence must be quickly integrated by tactical commanders to meet mission demands. Increasingly, unclassified commercial imagery and data acquired from conventional aircraft, unmanned aerial vehicles and satellites are being used by military and civilian analysts to populate coastal zone databases. This study assessed the suitability of commercially available satellite images for littoral warfare and homeland security operations. From the study, data that show the probabilities for extracting mandatory shoreline features from various images for maps produced at varying scale is… | J9: C | K9: Vojne/sigurnosne primjene snimaka | L9: C
A10: 6 | B10: 2013 | C10: Configuration and Specifications of an Unmanned Aerial Vehicle (UAV) for Early Site Specific Weed Management | D10: PLoS ONE | E10: Remote Sensing in Agriculture | F10: https://openalex.org/W2011270889 | G10: https://doi.org/10.1371/journal.pone.0058210 | H10: uav, unmanned aerial | I10: A new aerial platform has risen recently for image acquisition, the Unmanned Aerial Vehicle (UAV). This article describes the technical specifications and configuration of a UAV used to capture remote images for early season site- specific weed management (ESSWM). Image spatial and spectral properties required for weed seedling discrimination were also evaluated. Two different sensors, a still visible camera and a six-band multispectral camera, and three flight altitudes (30, 60 and 100 m) were tested over a naturally infested sunflower field. The main phases of the UAV workflow were the following: 1) mission planning, 2) UAV flight and image acquisition, and 3) image pre-processing. Three d… | J10: B | K10: Rano suzbijanje korova | L10: B
A11: 7 | B11: 2013 | C11: Estimating leaf carotenoid content in vineyards using high resolution hyperspectral imagery acquired from an unmanned aerial vehicle (UAV) | D11: Agricultural and Forest Meteorology | E11: Remote Sensing in Agriculture | F11: https://openalex.org/W2142087338 | G11: https://doi.org/10.1016/j.agrformet.2012.12.013 | H11: uav, unmanned aerial | I11: (sažetak nije dostupan — otvoriti poveznicu) | J11: B | K11: Karotenoidi u vinogradu | L11: B
A12: 8 | B12: 2015 | C12: Evaluation of an unmanned rotorcraft to monitor wintering waterbirds and coastal habitats in British Columbia, Canada | D12: Journal of Unmanned Vehicle Systems | E12: Wildlife-Road Interactions and Conservation | F12: https://openalex.org/W1892206252 | G12: https://doi.org/10.1139/juvs-2015-0019 | H12: uas, unmanned aircraft | I12: The effective protection of coastal and estuarine habitats requires reliable monitoring information on their use by waterbirds, and the use of small unmanned aircraft systems (UAS) may provide access to these habitats without disturbing birds. We evaluated the use of a rotary-wing UAS with a high-end consumer camera to identify and count wintering waterbirds at two coastal sites in British Columbia, Canada, in January 2015, and to map mudflat and marsh habitats. Photos of shorebirds, waterfowl, and seabird species were taken at varying altitudes, and disturbance of birds appeared minimal when the UAS was flown at heights ≥61 m. A ground resolution of ~1 cm/pixel was needed to discern plumage… | J12: A | K12: Vodene ptice i obalna staništa, mali UAS | L12: A
A13: 9 | B13: 2015 | C13: Deployment of an unmanned aerial system to assist in mapping an intermittent stream | D13: Hydrological Processes | E13: Flood Risk Assessment and Management | F13: https://openalex.org/W1692243462 | G13: https://doi.org/10.1002/hyp.10597 | H13: uas, unmanned aerial | I13: Abstract Recent growth in the capabilities of unmanned aerial vehicles and systems (UASs) as airborne platforms for collecting environmental data has been very rapid. There are now ample examples in the literature of UASs being deployed to map fine‐scale vegetation, glacial, soil and atmospheric conditions. The purported advantages of UASs are their ability to collect spatial data at lower cost, lower risk, higher resolution and higher frequency than ground surveys or satellite platforms. In this specific study, whether or not obtaining high‐resolution UAS imagery was advantageous for identifying an intermittent stream network was determined by comparing it with coarse‐scale satellite imager… | J13: A | K13: Kartiranje povremenog vodotoka UAS-om | L13: A
A14: 10 | B14: 2015 | C14: Wildlife research and management methods in the 21st century: Where do unmanned aircraft fit in? | D14: Journal of Unmanned Vehicle Systems | E14: Remote Sensing and LiDAR Applications | F14: https://openalex.org/W2130287418 | G14: https://doi.org/10.1139/juvs-2015-0021 | H14: uas, unmanned aircraft | I14: Since the turn of the century, emerging unmanned aircraft systems (UAS) have found increasingly diverse applications in wildlife science as convenient, very high-resolution remote sensing devices. Achieved or conceptualized applications include optical surveying and observation of animals, autonomous wildlife telemetry tracking, and habitat research and monitoring. As the technology continues to progress and interest from the wildlife science community grows, there may yet be much untapped potential for UAS to contribute to the discipline. We present a review of the published primary literature on the application of UAS in wildlife science and related fields. This is followed by a systematic… | J14: A | K14: Pregled: UAS u istraživanju divljači | L14: A
A15: 11 | B15: 2013 | C15: Method of Monitoring Cyanobacteria in Taihu Lake Based on the Low Altitude UAV with Visible-near Infrared Sensor | D15: Shandong Land and Resources | E15: Water Quality Monitoring Technologies | F15: https://openalex.org/W2354417035 | H15: uav | I15: Due to limitations of the access cycle,traditional means of satellite remote sensing is difficult to ensure the timeliness of data in time frequency. The low-altitude UnmannedAerialVehicle( UAV) equipped with a small light sensor,its maneuvers,rapid,economic and other advantages play an increasingly important role in the field of environmental monitoring. In order to meet monitoring requirements of cyanobacteria in TaihuLake,a visible-near infrared sensor monitoring method has been found based on the low-altitude UAV. On the basis of system planning and design platform,selecting Meiliang Lake area of Taihu lake to carry out the experiment. Based on previous experiences,using the Visible and … | J15: A | K15: Cijanobakterije u jezeru Taihu, UAV | L15: A
A16: 12 | B16: 2015 | C16: Using thermal infrared imagery produced by unmanned air vehicles to evaluate locations of ecological road structures | D16: Forestist | E16: Wildlife-Road Interactions and Conservation | F16: https://openalex.org/W2192551928 | G16: https://doi.org/10.17099/jffiu.76461 | H16: uav, uavs, unmanned aerial | I16: The aerial photos and satellite images are widely used and cost efficient data for monitoring and analysis of large areas in forestry activities. Nowadays, accurate and high resolution remote sensing data can be generated for large areas by using Unmanned Aerial Vehicles (UAV) integrated with sensors working in various spectral bands. Besides, the UAV systems (UAVs) have been used in interdisciplinary studies to produce data of large scale forested areas for desired time periods (i.e. in different seasons or different times of a day). In recent years, it has become more important to conduct studies on determination of wildlife corridors for controlling and planning of habitat fragmentation o… | J16: A | K16: Termalne UAV snimke za ekološke lokacije | L16: A
A17: 13 | B17: 2015 | C17: Comparison of atmospheric profile from ceilometer and UAV in the fog forest in central Taiwan. | D17: Japan Geoscience Union | E17: Remote Sensing and LiDAR Applications | F17: https://openalex.org/W2608167233 | H17: uav | I17: (sažetak nije dostupan — otvoriti poveznicu) | J17: A | K17: Atmosferski profil u maglenoj šumi, UAV | L17: A
A18: 14 | B18: 2009 | C18: INTEGRATION OF LOW COST GEOMATIC TECNIQUES TO SUPPORT THE ARCHITECTONICAL PROJECT. THE PERLO CASTLE AREA SURVEY | D18: PORTO Publications Open Repository TOrino (Politecnico di Torino) | E18: 3D Surveying and Cultural Heritage | F18: https://openalex.org/W92203316 | H18: uav, unmanned aerial | I18: In the high Tanaro Valley (Piedmont, Italy) the attestation of old pre-existence joined to the territory defence is possible to find numerous towers, castles, gouts and fortress. Today the most part of these cultural heritage are in ruin. Close to the municipality of Perlo few meters from the principal street, following a winding path is possible to arrive to a little hill; there the ruins of the old Castle of Perlo are hide from a rigorous vegetation. The old might of the fortress is lost today, is like an explosion of stone fragments swallow from the natural environment. The walls cut in some cases the hillok and the old towers are like rock spur. The requirement of the municipal administr… | J18: C | K18: Arhitektonski projekt, geomatika | L18: C
A19: 15 | B19: 2007 | C19: Biology of Apis dorsata in Vietnam | D19: Springer Link (Chiba Institute of Technology) | E19: Insect and Pesticide Research | F19: https://openalex.org/W4387391007 | G19: https://doi.org/10.1051/apido:2007002/pdf | H19: drone, drones | I19: This paper studies the biology of A. dorsata in the Melaleuca forest of Vietnam. The width of 158 A. dorsata combs was from 43–162 cm, and the height from 23–90 cm. About 3–4 weeks after nesting, a colony could store 4.1 $\pm$ 2.6 kg of honey. The thickness of the worker brood comb was 3.3 cm and of the drone was 3.7 cm, but that of the honey comb was possibly 19.0 cm. The width of 10 continuous drone cells (58.1 $\pm$ 1.4 cm, n = 90) is significantly larger than that of worker cells (55.7 $\pm$ 1.7, n = 330). The depth of drone cells was 19.0 $\pm$ 0.4 mm (n = 90) and of worker cells was 17.4 $\pm$ 1.5 mm (n = 225). The weights of the newly emerged worker, drone and queen bees were 159.9 $\… | J19: C | K19: „Drone“ = trut (Apis dorsata) | L19: C
A20: 16 | B20: 2015 | C20: Close Range Photogrammetry in the Survey of the Coastal Area Geoecological Conditions (on the Example of Portugal) | D20: Earth Sciences | E20: Coastal and Marine Dynamics | F20: https://openalex.org/W2196131291 | G20: https://doi.org/10.11648/j.earth.s.2015040501.17 | H20: drone, uav, unmanned aerial | I20: Close range digital photogrammetry, which involves the application of unmanned aerial vehicle (UAV), has been used in a growing number of diverse applications across different scientific disciplines. Our objective was to use the mentioned method in the survey of the contemporary geoecological conditions of the coastal area on the example of Portuguese northwest coastal zone. The coastal zone can be subdivided into two geomorphological sectors: Sector 1, between the Minho River and the town of Espinho, where the coastal segments consist of estuaries, sandy and shingle beaches with rocky outcrops, and Holocene dune systems. The estuaries and the foredunes in particular are very degraded by hum… | J20: A | K20: Geoekološki uvjeti obale, UAV fotogrametrija | L20: A
A21: 17 | B21: 2014 | C21: Study of the UAV for Application Plans and Landscape Analysis | D21: 한국전통조경학회지 | E21: Remote Sensing and LiDAR Applications | F21: https://openalex.org/W2519492495 | G21: https://doi.org/10.14700/kitla.2014.32.3.213 | H21: uav | I21: 본 연구는 최근 급속한 기술발전이 이루어지고 있는 (UAV)를 활용하여 지형분석에 적용하기 위한 실험적 연구로 드론과 자동 경로비행에 필요한 시스템을 구축하였다. 구축된 시스템을 이용하여 경로비행의 안정성을 검토하였으며, Waypoint를 이용한 경로비행 촬영을 실시하여 유용성을 검증한 결과는 다음과 같다. 첫째, 9.3ha에 달하는 면적에 대해 경로비행을 실시한 결과 준비시간을 포함하여 실측시간이 총40여분 소요되었으며, 지상부에서 인가한 고도와 속도를 일정하게 유지하는 것을 알 수 있었다. 또한 경로비행 시 지상부에서 설정한 Waypoint 지점에서 정확하게 촬영임무를 수행하여, multicopter를 이용한 사진실측의 효율성을 확인하였다. 둘째, 일반 실측용 무인항공기에 비해 가볍고 저렴한 multicopter와 디지털카메라를 이용하여 촬영의 기동성과 경제성을 확인하였으며, 촬영된 사진데이터의 정합과 DEM, DXF파일의 추출을 통해 수치지형도 보다 정밀한 지형분석이 가능하여 multicopter를 이용한 지형실측의 가능성을 확인하였다. 셋째, 하천내부에 대한 고해상 정사영상사진(20Cm급)을 제작함으로써 하천변일대에 대한 식생과 지형의 변화 등에 대한 분석이 가능한 것을 확인하였다. 또한 촬영지점의 GPS좌표에 대한 데이터베이스를 통해 미세지형의 변화 등과 같은 경관변화와 하천변 일대 또는 수림지 등에 대한 식생변화 등을 지속… | J21: B | K21: Analiza krajobraza/planiranje (Koreja) | L21: B
A22: 18 | B22: 2011 | C22: 3D model of Lugo’s Roman Walls (Galicia-Spain) using a Terrestrial Laser Scanner and Unmanned Aerial Vehicle. | D22: CAA 2012 | E22: 3D Surveying and Cultural Heritage | F22: https://openalex.org/W2496601862 | H22: uav, unmanned aerial | I22: Nowadays, there is a growing interest in application and development of new digital spatial technologies for 3D data capture, analysis and visualisation and subsequent documentation, investigation and conservation of cultural heritage. This paper presents a topographical survey with various spatial techniques which are combined to achieve a 3D model of Roman Walls in city of Lugo in northwest Spain. The walls were built in later part of 3 rd century and are located in historic city centre. They are one of best preserved in world and only one of it’s kind with completely intact walls. The entire length of walls is around 2 km, enclosing an area of 34 ha. In 2000, walls were inscribed on UNESC… | J22: C | K22: Rimske zidine, kulturna baština | L22: C
A23: 19 | B23: 2015 | C23: WILDLIFE MULTISPECIES REMOTE SENSING USING VISIBLE AND THERMAL INFRARED IMAGERY ACQUIRED FROM AN UNMANNED AERIAL VEHICLE (UAV) | D23: The international archives of the photogrammetry, remote sensing and spatial information sciences/International archives of the photogrammetry, remote sensing and spatial information sciences | E23: Wildlife Ecology and Conservation | F23: https://openalex.org/W2274694356 | G23: https://doi.org/10.5194/isprsarchives-xl-1-w4-241-2015 | H23: uav, unmanned aerial | I23: Abstract. Wildlife aerial surveys require time and significant resources. Multispecies detection could reduce costs to a single census for species that coexist spatially. Traditional methods are demanding for observers in terms of concentration and are not adapted to multispecies censuses. The processing of multispectral aerial imagery acquired from an unmanned aerial vehicle (UAV) represents a potential solution for multispecies detection. The method used in this study is based on a multicriteria object-based image analysis applied on visible and thermal infrared imagery acquired from a UAV. This project aimed to detect American bison, fallow deer, gray wolves, and elks located in separate … | J23: A | K23: Viševrsni popis divljači UAV-om | L23: A
A24: 20 | B24: 2014 | C24: Fault Detection of Aircraft System with Random Forest Algorithm and Similarity Measure | D24: The Scientific World JOURNAL | E24: Fault Detection and Control Systems | F24: https://openalex.org/W2111621334 | G24: https://doi.org/10.1155/2014/727359 | H24: uav, unmanned aircraft | I24: Research on fault detection algorithm was developed with the similarity measure and random forest algorithm. The organized algorithm was applied to unmanned aircraft vehicle (UAV) that was readied by us. Similarity measure was designed by the help of distance information, and its usefulness was also verified by proof. Fault decision was carried out by calculation of weighted similarity measure. Twelve available coefficients among healthy and faulty status data group were used to determine the decision. Similarity measure weighting was done and obtained through random forest algorithm (RFA); RF provides data priority. In order to get a fast response of decision, a limited number of coefficien… | J24: C | K24: Detekcija kvarova UAV-a | L24: C
A25: 21 | B25: 2011 | C25: Automatic Forest-Fire Measuring Using Ground Stations and Unmanned Aerial Systems | D25: Sensors | E25: Remote Sensing and LiDAR Applications | F25: https://openalex.org/W2052466191 | G25: https://doi.org/10.3390/s110606328 | H25: uas, unmanned aerial | I25: This paper presents a novel system for automatic forest-fire measurement using cameras distributed at ground stations and mounted on Unmanned Aerial Systems (UAS). It can obtain geometrical measurements of forest fires in real-time such as the location and shape of the fire front, flame height and rate of spread, among others. Measurement of forest fires is a challenging problem that is affected by numerous potential sources of error. The proposed system addresses them by exploiting the complementarities between infrared and visual cameras located at different ground locations together with others onboard Unmanned Aerial Systems (UAS). The system applies image processing and geo-location tec… | J25: A | K25: Mjerenje šumskih požara UAS-om | L25: A
A26: 22 | B26: 2014 | C26: Fellowship of the Snow | D26: The Journal of Trauma: Injury, Infection, and Critical Care | E26: Mind wandering and attention | F26: https://openalex.org/W2416225139 | G26: https://doi.org/10.1097/ta.0000000000000253 | H26: (nije u naslovu/sažetku) | I26: David H. Livingston, MD, WTA president.Well, that is a WTA (Western Trauma Association) moment! Classic Western Trauma! That would make the perfect WTA abstract! These phrases are a unique part of our lexicon and mythology. I do not think I have ever heard of an AAST (American Association for the Surgery of Trauma) moment and definitely not an SUS or American Surgical moment. There is no doubt that this is a special and unique organization such that being your president is the pinnacle of my professional career. When I thought about the most memorable addresses I have heard in this forum during the past 2 decades, they have been personal and have come from the heart. They also most commonly … | J26: C | K26: Nema UAV pojma (Fellowship of the Snow) | L26: C
A27: 23 | B27: 2013 | C27: Unmanned aerial vehicles as innovative remote sensing platforms for high‐resolution infrared imagery to support restoration monitoring in cut‐over bogs | D27: Applied Vegetation Science | E27: Remote Sensing and LiDAR Applications | F27: https://openalex.org/W1999949151 | G27: https://doi.org/10.1111/avsc.12024 | H27: uav, uavs, unmanned aerial | I27: Abstract Question Can UAV‐based NIR remote sensing support restoration monitoring of cut‐over bogs by providing valid information on species distribution and surface structure? Location Restored polders of the Uchter Moor, a bog complex in NW Germany. Methods We used autonomously flying quadrocopters, supplied with either a panchromatic or colour infrared calibrated small frame digital camera to generate high resolution images of the restored bog surface. We performed a two‐step classification process of automatic image segmentation and object‐based classification to distinguish between four pre‐defined classes (waterlogged bare peat, Sphagnum spp., Eriophorum vaginatum and Betula pubescens.… | J27: B | K27: UAV kao platforma za IR snimanje (primjena nejasna) | L27: B
A28: 24 | B28: 2005 | C28: NUEVA SEDE PARA CIENCIAS DEL MAR EN MAZATLÁN. ESTARÁ EN LA ISLA DE LA PIEDRA | D28: Gaceta UNAM (2000-2009) | E28: Environmental and Ecological Studies | F28: https://openalex.org/W1763529565 | H28: uas | I28: LA UNIDAD ACADEMICA MAZATLAN, DEL INSTITUTO DE CIENCIAS DEL MAR Y LIMNOLOGIA (ICMYL), TENDRA NUEVAS Y MEJORES INSTALACIONES EN LA ISLA DE PIEDRA, EN MAZATLAN, SINALOA -MISMAS QUE SE CONSTRUIRAN EN UN CORTO PLAZO-, MIENTRAS SU ACTUAL INMUEBLE LO CEDERA LA UNAM A LA UNIVERSIDAD AUTONOMA DE SINALOA (UAS). LA PROXIMA UNIDAD SE EDIFICARA EN UN PREDIO QUE LE OTORGO EL GOBIERNO DEL ESTADO. CONTARA CON UNA ZONA DE RESERVA ECOLOGICA: ACUARIOS, ESTANQUES EXPERIMENTALES, LABORATORIOS, UNA GRAN BIBLIOTECA SOBRE CIENCIAS DEL MAR QUE SERA REFERENTE NACIONAL Y LATINOAMERICANO Y, SOBRE TODO, SE PODRAN IMPULSAR LAS TAREAS DE DOCENCIA Y DIVULGACION DEL CONOCIMIENTO. AHI TAMBIEN HABRAN INSTALACIONES DE LA UAS.… | J28: C | K28: „UAS“ = Universidad Autónoma de Sinaloa | L28: C
A29: 25 | B29: 2009 | C29: Thermal and Narrowband Multispectral Remote Sensing for Vegetation Monitoring From an Unmanned Aerial Vehicle | D29: IEEE Transactions on Geoscience and Remote Sensing | E29: Remote Sensing in Agriculture | F29: https://openalex.org/W2133125644 | G29: https://doi.org/10.1109/tgrs.2008.2010457 | H29: uav, uavs, unmanned aerial | I29: Two critical limitations for using current satellite sensors in real-time crop management are the lack of imagery with optimum spatial and spectral resolutions and an unfavorable revisit time for most crop stress-detection applications. Alternatives based on manned airborne platforms are lacking due to their high operational costs. A fundamental requirement for providingusefulremote sensing products in agriculture is the capacity to combine high spatial resolution and quick turnaround times. Remote sensing sensors placed on unmanned aerial vehicles (UAVs) could fill this gap, providing low-cost approaches to meet the critical requirements of spatial, spectral, and temporal resolutions. This … | J29: B | K29: Praćenje vegetacije za upravljanje usjevima | L29: B
A30: 26 | B30: 2015 | C30: Locating chimpanzee nests and identifying fruiting trees with an unmanned aerial vehicle | D30: American Journal of Primatology | E30: Primate Behavior and Ecology | F30: https://openalex.org/W1956094000 | G30: https://doi.org/10.1002/ajp.22446 | H30: uav, uavs, unmanned aerial | I30: Monitoring of animal populations is essential for conservation management. Various techniques are available to assess spatiotemporal patterns of species distribution and abundance. Nest surveys are often used for monitoring great apes. Quickly developing technologies, including unmanned aerial vehicles (UAVs) can be used to complement these ground-based surveys, especially for covering large areas rapidly. Aerial surveys have been used successfully to detect the nests of orang-utans. It is unknown if such an approach is practical for African apes, which usually build their nests at lower heights, where they might be obscured by forest canopy. In this 2-month study, UAV-derived aerial imagery… | J30: A | K30: Gnijezda čimpanzi i plodonosna stabla, UAV | L30: A
A31: 27 | B31: 2011 | C31: The Analysis of Temporal and Spatial Variation on the Vegetation Area of the Siwha Tidat Flat | D31: Journal of Environmental Impact Assessment | E31: Ecology and Conservation Studies | F31: https://openalex.org/W210113691 | G31: https://doi.org/10.14249/eia.2011.20.3.349 | H31: uav | I31: This research is aim to analyze of changing landscape and according to phenological cycle from image information of coastal environment obtained by multi-media were analyzed by camera and satellite image. The digital camera and satellite image were used for tidal flat vegetation monitoring during the construction of Sihwa lake. The vegetation type and phenological cycle of Sihwa tidal flat have been changed with the Sihwa lake ecosystem. The environment changes of Sihwa tidal flat area and ecological change were analyzed by field work digital camera images and satellite images. The airborne, UAV and satellite images were classified with the changed elements of coastal ecological environment … | J31: A | K31: Vegetacija plimne ravnice, UAV snimke | L31: A
A32: 28 | B32: 2015 | C32: GreenHouse gas Observations of the Stratosphere and Troposphere (GHOST): Deployment of a Novel Shortwave Infrared Spectrometer On Board the NASA Global Hawk Unmanned Aerial Vehicle | D32: 2015 AGU Fall Meeting | E32: Atmospheric Ozone and Climate | F32: https://openalex.org/W2624798775 | H32: unmanned aerial | I32: (sažetak nije dostupan — otvoriti poveznicu) | J32: A | K32: Mjerenja stakleničkih plinova s Global Hawk UAV-a | L32: A
A33: 29 | B33: 2015 | C33: Managing 50,000 Acres of Private Land in Texas: Results of a recent 2,000 acre pedestrian, UAV, and vegetation survey in the Sierra Diablo Mountains. | D33: The 80th Annual Meeting of the Society for American Archaeology | E33: Forest Management and Policy | F33: https://openalex.org/W1033501934 | H33: uav | I33: (sažetak nije dostupan — otvoriti poveznicu) | J33: A | K33: Popis vegetacije privatnog zemljišta, UAV | L33: A
A34: 30 | B34: 2015 | C34: PERFORMANCE CHARACTERISTIC MEMS-BASED IMUs FOR UAVs NAVIGATION | D34: The international archives of the photogrammetry, remote sensing and spatial information sciences/International archives of the photogrammetry, remote sensing and spatial information sciences | E34: Remote Sensing and LiDAR Applications | F34: https://openalex.org/W1887247996 | G34: https://doi.org/10.5194/isprsarchives-xl-1-w4-337-2015 | H34: uav, uavs, unmanned aerial | I34: Abstract. Accurate 3D reconstruction has become essential for non-traditional mapping applications such as urban planning, mining industry, environmental monitoring, navigation, surveillance, pipeline inspection, infrastructure monitoring, landslide hazard analysis, indoor localization, and military simulation. The needs of these applications cannot be satisfied by traditional mapping, which is based on dedicated data acquisition systems designed for mapping purposes. Recent advances in hardware and software development have made it possible to conduct accurate 3D mapping without using costly and high-end data acquisition systems. Low-cost digital cameras, laser scanners, and navigation syst… | J34: C | K34: MEMS IMU za navigaciju UAV-a | L34: C
A35: 31 | B35: 2014 | C35: Research of Low-altitude Photogrammetry Implementation Strategy of China's Ancient Circumvallation Project of Surveying and Mapping of Ming Dynasty Circumvallation (Southern Wall Section) | E35: Remote Sensing and LiDAR Applications | F35: https://openalex.org/W2204050869 | H35: uav, unmanned aerial | I35: Most of the existing ancient circumvallation in China today is in the natural environment and the environment has never been cleaned up. As the blockings caused by the vegetation on the circumvallation itself, the surrounding vegetations, the constructions and other surface features affect the terrestrial laser scanning and the low altitude photogrammetry, there are often incomplete three‐dimensional points cloud data. Therefore, in the prior period of conservation works, surveying and mapping are difficult to implement under this circumstance. In this paper, based on the surveying and mapping of ZhengDing Ming Circumvallation and some other ancient circumvallation in northern China, charact… | J35: C | K35: Stare utvrde, fotogrametrija baštine | L35: C
A36: 32 | B36: 2015 | C36: Phenotyping in the fields: dissecting the genetics of quantitative traits and digital farming | D36: New Phytologist | E36: Wheat and Barley Genetics and Pathology | F36: https://openalex.org/W2135362361 | G36: https://doi.org/10.1111/nph.13529 | H36: unmanned aerial | I36: ‘… development of novel approaches for studying traits like nutrient, water and radiation-use efficiency must be developed under field conditions …’ Crop production has to substantially increase within the next decades, following an already long history of changing plant traits to produce desired characteristics. Thus, plant performance has been substantially influenced during domestication and post-domestication selection, including modern breeding. In the group of Roberto Papa (University of Ancona, Italy) the complementing use of genomic analysis, molecular phenotyping, and high-throughput phenotyping of wild and domesticated common bean accessions revealed a tremendous impact of specific… | J36: B | K36: Fenotipizacija, digitalna poljoprivreda | L36: B
A37: 33 | B37: 2015 | C37: Inventory of Small Forest Areas Using an Unmanned Aerial System | D37: Remote Sensing | E37: Remote Sensing and LiDAR Applications | F37: https://openalex.org/W1522525389 | G37: https://doi.org/10.3390/rs70809632 | H37: uas, unmanned aerial | I37: Acquiring high spatial and temporal resolution imagery from small unmanned aerial systems (sUAS) provides new opportunities for inventorying forests at small scales. Only a few studies have investigated the use of UASs in forest inventories, and the results are inconsistent and incomplete. The present study used three-dimensional (3D) variables derived from UAS imagery in combination with ground reference data to fit linear models for Lorey’s mean height (hL), dominant height (hdom), stem number (N), basal area (G), and stem volume (V). Plot-level cross validation revealed adjusted R2 values of 0.71, 0.97, 0.60, 0.60, and 0.85 for hL, hdom, N, G, and V, respectively, with corresponding RMSE … | J37: A | K37: Inventura malih šumskih površina UAS-om | L37: A
A38: 34 | B38: 2013 | C38: Low-cost lightweight airborne laser-based sensors for pipeline leak detection and reporting | E38: Atmospheric and Environmental Gas Dynamics | F38: https://openalex.org/W3179232040 | H38: uav, unmanned aerial | I38: Laser sensing enables aerial detection of natural gas pipeline leaks without need to fly through a hazardous gas plume. This paper describes adaptations of commercial laser-based methane sensing technology that provide relatively low-cost lightweight and battery-powered aerial leak sensors. The underlying technology is near-infrared Standoff Tunable Diode Laser Absorption Spectroscopy (sTDLAS). In one configuration, currently in commercial operation for pipeline surveillance, sTDLAS is combined with automated data reduction, alerting, navigation, and video imagery, integrated into a single-engine single-pilot light fixed-wing aircraft or helicopter platform. In a novel configuration for mapp… | J38: A | K38: Detekcija curenja plina (metan) laserskim senzorom na UAV-u | L38: A
A39: 35 | B39: 2009 | C39: Development of low-cost and flexible vegetation monitoring system using small unmanned aerial vehicle | D39: 2009 ICCAS-SICE | E39: Remote Sensing and LiDAR Applications | F39: https://openalex.org/W3150939766 | H39: unmanned aerial | I39: (sažetak nije dostupan — otvoriti poveznicu) | J39: A | K39: Sustav praćenja vegetacije malim UAV-om | L39: A
A40: 36 | B40: 2015 | C40: Unmanned aerial vehicle application for mapping individual plants: the case of the Nebrodi beech forest | E40: Remote Sensing and LiDAR Applications | F40: https://openalex.org/W2944501415 | H40: unmanned aerial | I40: (sažetak nije dostupan — otvoriti poveznicu) | J40: A | K40: Kartiranje pojedinačnih stabala bukove šume | L40: A
A41: 37 | B41: 2012 | C41: Adaptive gas source localization strategies and gas distribution mapping using a gas-sensitive micro-drone | E41: Insect Pheromone Research and Control | F41: https://openalex.org/W339750658 | H41: drone | I41: In this paper we exemplify how to address environmental monitoring tasks with a gas-sensitive micro-drone and present two different approaches to locate gas emission sources. First, we sent the mic ... | J41: A | K41: Kartiranje raspodjele plina mikro-dronom | L41: A
A42: 38 | B42: 2012 | C42: A flexible unmanned aerial vehicle for precision agriculture | D42: Precision Agriculture | E42: Remote Sensing in Agriculture | F42: https://openalex.org/W2151499786 | G42: https://doi.org/10.1007/s11119-012-9257-6 | H42: unmanned aerial | I42: (sažetak nije dostupan — otvoriti poveznicu) | J42: B | K42: UAV za preciznu poljoprivredu | L42: B
A43: 39 | B43: 2013 | C43: AlpSAR 2012-13, a Field Experiment on Snow Observations and Parameter Retrievals with Ku- and X-Band Radar | D43: Scholar Works (Boise State University) | E43: Cryospheric studies and observations | F43: https://openalex.org/W292798094 | H43: uav | I43: In order to support the development of observation techniques and inversion algorithms for the retrieval of physical snow parameters from high frequency radar backscatter data, field campaigns have been performed in previous winters in Northern Finland, Canada and United States. In winter 2012-13 additional field campaigns take place in the Austrian Alps within the AlpSAR experiment. AlpSAR is aimed at enhancing the experimental data base on radar backscatter by covering different snow regimes and terrain types than in previous campaigns. A main objective of the campaign is the testing and validation of algorithms for retrieval of the water equivalent (SWE) of winter snow cover over differen… | J43: B | K43: Snježna opažanja, UAV snimanje kao pomoćni podatak | L43: B
A44: 40 | B44: 2014 | C44: Forestry Reports | D44: Journal of Forestry | E44: Plant Ecology and Soil Science | F44: https://openalex.org/W4251900152 | G44: https://doi.org/10.5849/jof.14-899 | H44: (nije u naslovu/sažetku) | I44: (sažetak nije dostupan — otvoriti poveznicu) | J44: C | K44: Nema UAV pojma (Forestry Reports) | L44: C
A45: 41 | B45: 2013 | C45: Lighter-than-air stationary observation platforms | D45: RMIT Research Repository (RMIT University Library) | E45: Aerospace Engineering and Energy Systems | F45: https://openalex.org/W2254251245 | H45: uavs | I45: The benefits of stationary aerial platforms for continuous observation of a fixed area are evident in cases such as natural disasters, environmental monitoring, intelligence gathering, etc. A still photo is useful but temporal information, over many days, is in many cases critical to determine the best possible response. Satellites are the most obvious instrument for this purpose, but have limitations in terms of positioning time, time on station and cost. Conventional UAVs are another solution, but have limited endurance. Technological developments in lighter-than-air (LTA) systems have made them an attractive option for carrying a sensor suite to high altitudes. For example, using light we… | J45: C | K45: Platforme lakše od zraka; UAV samo spomenut | L45: C
A46: 42 | B46: 2015 | C46: Photogrammetry with an Unmanned Aerial System to Assess Body Condition and Growth of Blainville's Beaked Whales | E46: Marine animal studies overview | F46: https://openalex.org/W2597748452 | H46: uas, unmanned aerial | I46: Abstract : We propose to use the NOAA APH-22 marine hexacopter as an Unmanned Aerial System (UAS) to obtain vertical images of whale lengths and width profiles. This small, battery-powered platform is quiet, cost-effective and safe to operate from small boats, and can hover over animal groups. We will launch the hexacopter from a boat platform to fly short missions over beaked whales when they are sighted close-by at the surface, obtaining high resolution digital images from a height of approximately 30m. We will validate this system for beaked whales during a field trial in summer 2016 south of Great Abaco Island, northern Bahamas, where a photo-identification study over 18 years has demons… | J46: A | K46: Fotogrametrija kitova UAS-om | L46: A
A47: 43 | B47: 2012 | C47: Path planning of UAV in water environmental monitoring | E47: Robotic Path Planning Algorithms | F47: https://openalex.org/W2381572317 | H47: uav, unmanned aerial | I47: In water environmental monitoring,unmanned aerial vehicle(UAV) can not monitor all the areas at a time due to the influence of its physical properties and risk factor.So it’s extremely important to bring the service efficiency of the UAV into full play.The optimal path planning problem of the UAV for water environmental monitoring is presented and a mathematic model of the problem is built up.On the basis of this,a geneticsimulation annealing algorithm is presented.The computational amount is decreased,a method combined of both grid space indication and directional code is adopted.The simulation test result indicates that this method can get a better solution than genetic algorithm and it ca… | J47: A | K47: Planiranje putanje UAV-a za praćenje voda | L47: A
A48: 44 | B48: 2005 | C48: The Dulcimore | D48: Appalachian heritage | E48: Irish and British Studies | F48: https://openalex.org/W4206478398 | G48: https://doi.org/10.1353/aph.2005.0038 | H48: (nije u naslovu/sažetku) | I48: FEATURED AUTHOR—FICTION The Dulcimore Emma Bell Miles THE MOUNTING SUMMER had at last escaped the grasp of the April chill, and the season's growth came on with a headlong rush. The forest was one rustling loom of life-stuff, everywhere thrilling to million-tinted glories of summer beauty and abundance. Between twin hills that lay against the sky, dark and softly rounded as the breasts of a slave-mother, the old smithy nestled. It was a log structure, low and windowless, and lighted like a grotto withblue and greenish reflections from the hot sunshine outside. The young giant in the leather apron was clanking steadily on with his task, albeit he had a visitor. Straight from trysting with the… | J48: C | K48: Nema UAV pojma (The Dulcimore) | L48: C
A49: 45 | B49: 2012 | C49: Design and implementation of a forest fire monitoring system using a miniature unmanned aerial vehicle | D49: Journal of Zhejiang A & F University | E49: Fire effects on ecosystems | F49: https://openalex.org/W2389498532 | H49: uav, unmanned aerial | I49: To explore a new means of forest fire monitoring and to improve the management level of forest safety,real-time video and computer technology were combined to develop a new piece of forest fire monitoring equipment.This equipment and a miniature unmanned aerial vehicle(UAV) together formed the miniature aerial forest fire monitoring system.Sampled RGB value of image pixels,a smoke recognition model was established by using the statistical product and service solution(SPSS) for cluster analysis.The model had been improved for smoke spectrum and noise reduction,cloud recognize more than 77% smoke pixels of test images.With the recognition model,immediate fire detection and warning could occur.… | J49: A | K49: Sustav praćenja šumskih požara mini-UAV-om | L49: A
A50: 46 | B50: 2015 | C50: Unmanned Aircraft Systems complement biologging in spatial ecology studies | D50: Ecology and Evolution | E50: Wildlife Ecology and Conservation | F50: https://openalex.org/W1920083332 | G50: https://doi.org/10.1002/ece3.1744 | H50: uas, unmanned aircraft | I50: The knowledge about the spatial ecology and distribution of organisms is important for both basic and applied science. Biologging is one of the most popular methods for obtaining information about spatial distribution of animals, but requires capturing the animals and is often limited by costs and data retrieval. Unmanned Aircraft Systems (UAS) have proven their efficacy for wildlife surveillance and habitat monitoring, but their potential contribution to the prediction of animal distribution patterns and abundance has not been thoroughly evaluated. In this study, we assess the usefulness of UAS overflights to (1) get data to model the distribution of free-ranging cattle for a comparison wit… | J50: A | K50: UAS + biologging u prostornoj ekologiji | L50: A
A51: 47 | B51: 2006 | C51: The Whalesong | D51: ScholarWorks - UA (University of Alaska System) | E51: Higher Education Research Studies | F51: https://openalex.org/W7139151544 | H51: uas | I51: Changes on the menu for UAS cafeteria -- Board of Regents approve 7 percent tuition hike to support operations costs -- What's going on? -- Learning central - encouraging good study habits -- UA in brief -- Student liaisons to the UA administration -- Whalesong gets a tune-up -- Osama's been lost in political games -- Spotlight: Chef feeds student spirit -- Students and faculty fight fires in the name of safety -- Marine Highway offers a scenic and secure alternative to air travel -- Iran exports student, as well as oil -- Fairbanks in budget crisis effects UAF students -- Blended sport lures students into the woods -- And you thought that you had heard some strange arguments... -- Ketchikan… | J51: C | K51: „UAS“ = sveučilišna kafeterija | L51: C
A52: 48 | B52: 2015 | C52: The use of conservation drones in ecology and wildlife research | D52: Journal of Ecology and Environment | E52: Land Use and Ecosystem Services | F52: https://openalex.org/W1984289423 | G52: https://doi.org/10.5141/ecoenv.2015.012 | H52: drones | I52: Conservation drones are remote-controlled devices capable of collecting information from difficult-to-access places while minimizing disturbance. Although drones are increasingly used in many research disciplines, their application to wildlife research remains to be explored in depth. This paper reports on the use of Phantom 2 Vision+ for monitoring areas in two national parks in South Korea. The first research area was conducted in Chiaksan National Park, and the second in Taeanhaean National Park. The aim of this research is to introduce ecologists and researchers alike to conservation drones and to show how these new tools have are fundamentally helping in the development of natural scien… | J52: A | K52: Konzervacijski dronovi u ekologiji | L52: A
A53: 49 | B53: 2012 | C53: Neuro-optimal control of an unmanned helicopter | D53: The Journal of Defense Modeling and Simulation Applications Methodology Technology | E53: Adaptive Dynamic Programming Control | F53: https://openalex.org/W2029059986 | G53: https://doi.org/10.1177/1548512912450369 | H53: uavs, unmanned aerial | I53: Helicopter unmanned aerial vehicles (UAVs) can be extensively used for military missions as well as in civil operations, ranging from multi-role combat support and search and rescue, to border surveillance and forest fire monitoring. Helicopter UAVs are underactuated nonlinear mechanical systems with correspondingly challenging controller designs. This paper presents an optimal controller design for tracking of an underactuated helicopter using an adaptive critic neural network (NN) framework. The online approximator-based controller learns the infinite-horizon continuous-time Hamilton–Jacobi–Bellman (HJB) equation and then calculates the corresponding optimal control input that minimizes th… | J53: C | K53: Upravljanje bespilotnim helikopterom | L53: C
A54: 50 | B54: 2015 | C54: Surveying applications of photogrammetric UAVs -a comparison with conventional survey techniques | E54: 3D Surveying and Cultural Heritage | F54: https://openalex.org/W2467989596 | H54: drones, uav, uavs, unmanned aerial | I54: Unmanned Aerial Vehicles – or Drones is a broad term for a range of aerial vehicles that are not manned. UAVs are capable of capturing ground spatial data by mounting a camera onto the UAV to capture photogrammetric images. These photogrammetric images are able to be geo-referenced using a process called ortho-rectification. From these geo-referenced images spatial data can be obtained and output such as digital elevation models. With the ever increasing access and reduced costs to this type of technology this may become a viable tool for the modern surveyor to increase their efficiency and reduce workplace risks. The modern surveyor must continually adapt their field practices to match… | J54: C | K54: Geodetska izmjera UAV-om (bez okolišne primjene) | L54: C

Sheet Strogi_upit
A1: Osjetljivost na strogi upit: D AND E NOT (crop OR crops OR yield OR agriculture OR agricultural OR wheat OR maize OR rice OR soybean OR vineyard OR phenotyping OR weed OR weeds); OpenAlex, dohvat 27. 8. 2026.
A3: Godina | B3: core_drone_env | C3: strict_noagri | D3: omjer strict/core
A4: 2005 | B4: 28 | C4: 24 | D4: =C4/B4 -> 0.85714286
A5: 2006 | B5: 37 | C5: 35 | D5: =C5/B5 -> 0.94594595
A6: 2007 | B6: 43 | C6: 38 | D6: =C6/B6 -> 0.88372093
A7: 2008 | B7: 44 | C7: 38 | D7: =C7/B7 -> 0.86363636
A8: 2009 | B8: 55 | C8: 48 | D8: =C8/B8 -> 0.87272727
A9: 2010 | B9: 55 | C9: 48 | D9: =C9/B9 -> 0.87272727
A10: 2011 | B10: 75 | C10: 65 | D10: =C10/B10 -> 0.86666667
A11: 2012 | B11: 105 | C11: 84 | D11: =C11/B11 -> 0.8
A12: 2013 | B12: 157 | C12: 124 | D12: =C12/B12 -> 0.78980892
A13: 2014 | B13: 185 | C13: 132 | D13: =C13/B13 -> 0.71351351
A14: 2015 | B14: 330 | C14: 266 | D14: =C14/B14 -> 0.80606061
A15: 2016 | B15: 507 | C15: 394 | D15: =C15/B15 -> 0.77712032
... A24: 2025 | B24: 4747 | C24: 3309 | D24: =C24/B24 -> 0.69707183
A26: CAGR 2005–2025 | B26: =(B24/B4)^(1/20)-1 -> 0.29259675 | C26: =(C24/C4)^(1/20)-1 -> 0.27930553
A27: CAGR 2015–2025 | B27: =(B24/B14)^(1/10)-1 -> 0.30554104 | C27: =(C24/C14)^(1/10)-1 -> 0.28671248
A29: Tumačenje: omjer pada s ~0,86 (2005.) na ~0,70 (2025.) — udio poljoprivrednih radova u upitu raste; strogi upit raste ~1,4 postotna boda sporije godišnje. Trend i zaključak o zasićenju udjela ostaju isti (provjeriti u MATLAB-u s opt.numerator = 'strict_noagri').
